{"index": {"BottleRocket Entertainment": [5563], "Interworks Unlimited, Inc.": [10362], "Human Entertainment": [5905], "Westwood Studios": [6344, 8230], "ThatGameCompany": [5203], "Cing": [4282, 8381], "Extra Mile Studios": [8288], "Petroglyph": [7189, 7668, 9723, 10632], "Ice-Pick Lodge": [9308], "Now Production": [2238, 3318, 4050, 4874, 4928, 5625, 5929, 6045, 6149, 6272, 7294, 7405, 7758], "Ubisoft Reflections, Ivory Tower": [761, 2329, 6036], "Paon Corporation": [2391, 6063, 8405], "Cooking Mama Limited": [1775, 2955], "Camouflaj, LLC": [10321], "Omega Force, Tecmo Koei Games": [1255], "XS Games": [9111, 10413], "Related Designs": [4249], "2K Games": [3719, 6059, 6353, 6683, 6818, 7871], "Runic Games": [7967], "1st Playable Productions": [8387], "EA Montreal": [824, 1271, 1594, 1812, 1847, 2959, 3992, 4886], "Electronic Arts, EA Redwood Shores": [1462], "SCEA, Zindagi Games": [232], "Synetic": [8170], "EA Salt Lake": [1477, 1507, 2058, 2722, 3604], "EM Studios": [6804], "Acquire": [627, 2564, 2847, 2855, 3970, 5258, 5292, 5441, 7791, 9631, 9763], "EA Sports Big": [809, 2744, 3277], "Pendulo Studios": [8340, 8919], "Whitebear": [9226], "LucasArts, Red Fly Studio": [1994], "Silicon Studio": [2620], "Empire Interactive": [9065], "ChunSoft": [5471], "Atomic Planet Entertainment": [2519, 3367, 4394, 6574, 8674, 8851, 8969, 9036, 9477], "ValuSoft": [6907, 7991, 9328, 10201], "Milestone": [7333, 9931], "ChaYoWo Games": [10223], "Playrix Entertainment": [8565, 9292], "Digital Extremes": [2042, 3003, 3042, 3597, 4081, 4838, 6425, 7157, 10355], "Virtual Air Guitar Company": [6543], "Stainless Games": [9960, 10555], "Razorworks": [3045], "DreamFactory": [1526, 7151, 8798, 9289], "Ornith": [4460], "StudioBlack Games": [8033], "Kush Games": [953, 1752, 2091, 2433, 2484, 2659, 3200, 3344, 3693, 4005, 4164, 4790, 4869, 4957, 5789, 6328, 6520, 6705, 7000, 7484, 7706, 8061, 10508], "Jellyvision, Iron Galaxy Studios": [5269, 5280, 5736], "Hangar 13": [711, 2401, 5479], "Mindscape Inc., Mindscape": [6767], "DreamCatcher Interactive": [9256], "Bohemia Interactive": [6370, 7111, 8898, 9438], "Number None Inc., Knockout Games": [9528], "LucasArts, Krome Studios": [3281, 4684, 9627], "Bethesda Game Studios": [44, 67, 89, 146, 194, 224, 227, 1129, 1536], "3G Studios": [1151], "Atari": [1578, 3347, 5328, 6407, 6592, 7729, 7817, 10647], "Boomzap": [10224], "Zoe Mode, HB Studios Multimedia": [4481, 4533, 7824], "Massive Entertainment": [234, 560, 3425, 9220, 9236], "Sensory Sweep": [8002, 8532], "Creatures Inc.": [1260, 2007], "Genki": [931, 1672, 5464, 5687, 7246, 7997, 8004, 8664, 9439, 10518], "Sims": [4389, 5781], "Ready at Dawn": [2476, 2672], "Blue 52": [9128], "Interplay": [8207, 8629], "Sega AM2": [710, 1253, 1386, 4106, 4440, 6229, 7242, 7986, 8637], "Sega AM3": [1446], "Noise Inc.": [3718], "Turtle Rock Studios": [1563, 2336, 5544], "Aqua Pacific, In2Games": [7062, 9489], "Kunos Simulazioni": [8274, 10298], "Flight-Plan": [6374], "Crave": [4350, 5312, 5705, 6780, 7004, 7447, 7556, 7654, 7684, 7867, 8293, 8485, 8867, 8970, 9755], "Activision, Behaviour Interactive": [9628], "Overworks": [1573, 5064, 7486], "Zoe Mode": [951, 1249, 2911, 2999, 3315, 3689, 4720, 4846, 4885, 5055, 5980, 8300, 8705], "Marvelous Entertainment": [1859, 4305], "Matrix Software": [5007, 8544], "EKO Software": [5876, 5879, 8506, 8730, 8958, 9511], "Vatra": [3117], "Aspyr": [10057, 10565], "4J Studios": [323, 6741, 6820, 6933, 10430], "Incognito Inc.": [1012, 1434, 2755, 3075, 5737], "Raven Software": [456, 650, 1709, 1857, 2339, 2792, 3211, 3626, 3710, 4067, 4795, 4876, 8752, 9280, 9903, 10445], "Alternative Software": [9901], "Gas Powered Games": [3896, 5496, 8294, 8872, 9145, 9676, 9770], "Equinoxe": [2123], "Ratbag": [3028, 5158, 5320, 7873], "Warner Bros. Interactive Entertainment": [6227], "Zipper Interactive": [249, 355, 610, 779, 1715], "Pipeworks Software, Inc.": [80, 499, 2118, 2596, 3085, 3522, 3702, 3979, 5173, 5535, 6092, 6406, 6799, 6912, 9003, 9042], "Bungie Software, Bungie": [24, 91, 108, 291, 1244, 3846], "Activision, FreeStyleGames": [4484, 5500], "Jupiter Corporation": [1762], "Kadokawa": [7330, 8726, 10535], "Creative Assembly": [1325, 1385, 2084, 2263, 2483, 2876, 3226, 3635, 3996, 4415, 4851, 5050, 5818, 6123, 6310, 6558, 6645, 7193, 7376, 8110, 9378, 9961], "Opus": [4073, 4497, 4686, 4728, 5751, 8952, 9813], "Minds-Eye Productions": [9734], "Microsoft Game Studios Japan": [6937], "Spellbound": [5601, 7429, 10185], "Virtual Play Inc.": [10155], "Trion Worlds": [2212, 2605, 3843, 5276], "The Sims Studio": [52, 521, 643, 776, 1008, 2183, 2247, 2361, 2587, 3122, 3921, 6044, 7777], "Zombie Studios": [3756, 4384, 6750, 9939], "Banpresto, SoftMax": [4218], "Climax Studios": [7635, 10564], "Left Field Productions": [4670, 4804, 4993, 6506, 7297, 7327, 7854, 8089], "SmartDog": [8657], "Gratuitous Games": [5003, 5324, 6280], "Graffiti Entertainment": [6731, 8184, 8767], "Gameness Art Software": [9696], "Left Field Productions, Zoo Games": [8428], "Big Blue Box": [418], "High Moon Studios": [183, 188, 3190, 3239, 3252, 3288, 3572, 3607, 3880, 4048, 4288, 4396, 5212, 6696], "Iron Galaxy Studios": [4119, 8662, 9408], "Asobo Studio": [1806, 2000, 2541, 2621, 2905, 3027, 3899, 4146, 4810, 4840, 6300, 8581, 9285, 9429, 9879], "Farsight Technologies": [10096], "Rockstar Studios": [693, 838, 3309], "Tamsoft, D3Publisher": [4815], "Behaviour Interactive": [2663, 2973, 5319, 5609, 6355, 6620, 6744, 7239, 7348, 7483, 8681, 8840], "Kaos Studios": [970, 1695, 2666, 9833], "Master Creating": [9933], "Amuze": [3633, 9087, 9954], "Southend Interactive": [4729], "Sega, French-Bread": [5958], "Humongous Entertainment, Mistic Software": [8296], "From Software": [460, 619, 706, 816, 1145, 1531, 1921, 2029, 2221, 3446, 3559, 3567, 3865, 3958, 4232, 4385, 4627, 4780, 5166, 5327, 5433, 5476, 5550, 5740, 5772, 5922, 6230, 6611, 6631, 6885, 6964, 7286, 7413, 8006, 8190, 8474, 8623, 9151, 9873], "Shaba Games": [799, 1766, 2752, 2937, 3099, 3474, 5146, 5999, 7467, 8588], "Examu, Marvelous Inc.": [8981], "777 Studios": [10325], "PQube": [9181], "Irrational Games, 2K Marin": [379, 3438], "Acclaim Studios Cheltenham": [449, 2400, 3510, 4451, 6950, 7038, 8243, 8689, 9904, 9978], "GCP1": [5467], "Rovio Mobile, Rovio Entertainment": [4612, 4917, 5982, 7435], "Prope, Kadokawa": [6814], "EA Sports, EA Canada": [2373, 3023], "Artech Studios": [4651, 5485, 5932, 7453, 8509, 8807], "Artoon": [2657, 3072, 5252, 8423], "Milestone S.r.l": [3612, 3853, 4784, 5065, 5075, 5205, 5238, 5352, 5608, 5669, 5678, 5800, 6470, 6797, 6969, 7195, 7708, 8577, 8704, 8859, 8889, 9297, 9410, 9469, 9538, 10299, 10347, 10372, 10530, 10541, 10542, 10568, 10607], "Traveller's Tales": [109, 117, 237, 290, 329, 412, 438, 474, 504, 517, 727, 884, 887, 955, 1019, 1038, 1105, 1122, 1146, 1187, 1194, 1241, 1274, 1467, 1472, 1486, 1558, 1559, 1599, 1671, 1720, 1732, 2075, 2252, 2309, 2343, 2372, 2505, 2764, 3225, 3280, 3423, 3494, 3777, 4369, 4414, 4708, 5101, 5363, 5695, 5839, 6247, 6251, 7016, 8115, 8316, 8771, 9001, 9173, 9514, 9548, 10243], "WayForward": [3502, 4794, 5241, 5344, 6789, 7434, 7509, 7636, 8309, 8412, 8613, 8792, 10296], "Valuewave Co.,Ltd.": [2525, 4291, 5686], "SuperMassive Games": [807, 3582], "Bit Town": [5114], "Silver Wish Games": [8222], "Seamless Entertainment, Inc.": [7185], "Bandai Namco Games": [795, 1205, 1504, 1816, 2045, 2822, 3133, 3471, 3482, 4130, 5019, 5605, 7053, 8892], "Sick Puppies": [6291], "Gaijin Games": [7618], "LightBox Interactive": [4316], "Treyarch, Infinity Ward": [8419], "TimeGate Studios, Day 1 Studios": [7629], "Top Heavy Studios": [6500, 8083], "989 Sports": [1514, 1689, 2245, 3287, 3402, 3473, 3486, 3516, 3988, 4181, 4551, 4673, 4960, 5027, 5038, 5362, 5435, 5460, 5580, 6055, 6142, 6177, 6380], "Dimps Corporation, Namco Bandai Games": [1802, 2981], "Curious Pictures": [6703, 6829], "UBlart Montpellier": [1517, 1951, 2694, 7929], "Telenet": [7751], "Arc System Works": [2066, 2590, 3467, 3769, 3849, 4116, 4203, 6276, 6298, 6471, 6588, 6719, 7350, 7568, 7599, 7670, 7753, 7766, 8194, 8315, 8425, 8894, 9016, 9085, 9237, 9419, 9944, 10436], "MASA Group": [5183], "505 Games": [6020, 7283, 7436, 7952, 7969, 8447, 8719, 9393, 9629], "49Games": [1182, 3535, 5663, 7031, 7406, 7623, 7894, 7992, 9411, 9509, 9667, 10318, 10621], "Disney Interactive Studios, Land Ho!": [6043, 6827], "Black Rock Studio": [463, 1724, 2468, 8984], "UFO Interactive": [5950, 8836, 9743, 10003, 10108], "Sunrise Interactive": [3306], "Kylotonn": [5925, 6262, 9260], "Sanzaru Games": [2196, 2459, 2711, 4011, 6765, 8189], "Playlogic, The Game Factory": [5889, 5911], "Delta Factory": [9083], "Red Fly Studio": [1782, 3254, 5670, 6202], "Le Cortex": [6179], "Prokion": [4640], "Cavia Inc.": [909, 1438, 2293, 2413, 2567, 2923, 3836, 4286, 5881, 6329, 6578, 7282, 10330], "Edge Entertainment, Anima Project": [9791], "Ubisoft Sofia": [1130], "Artdink": [4194, 8169], "Airtight Games": [3822, 4080, 4153, 5995, 6454, 7279, 8568, 10213], "Knowledge Adventure Inc.": [3427], "Wargaming.net": [4353, 9923], "DC Studios": [7736], "Infinity Ward": [18, 31, 33, 41, 42, 81, 174, 233, 359, 476, 617, 1294, 1738, 6479, 8356, 9023, 9855], "EA Redwood Shores, EA Salt Lake": [1368], "React Games": [10528], "Razorworks Studios": [1505, 4599, 5381, 6199, 6339, 7130, 7589, 9766], "Namco Bandai Games": [403, 665, 902, 1046, 1535, 1804, 2811, 3888, 4135, 4276, 5356, 5546, 5707, 8244], "Babylon Software": [10173, 10391], "Angel Studios": [425, 2982], "Flying Lab Software": [10193], "Katauri Interactive": [10579], "MBA International": [8276], "Game Sauce": [5577], "Dreamcatcher": [7557], "Neverland": [3736, 5026, 5454, 6925, 7344, 8659], "Sledgehammer Games": [56, 125, 3456], "Nippon Ichi Software": [2606, 2846, 3976, 3980, 4340, 5213, 5329, 5600, 6313, 6541, 6735, 8200, 9942], "Blizzard Entertainment": [94, 133, 151, 206, 566, 589, 661, 701, 703, 805, 858, 896, 1011, 1094, 1423, 2782, 2794, 3044, 4057, 6547, 8796], "Jack of All Games": [5631, 6281, 10500], "Irem": [5165, 5583, 9177], "Targem Games, TopWare Interactive": [8943, 9553], "ImaginEngine": [6717, 7373], "Viva Media, Viva Media, LLC": [9316], "Buka Entertainment, Targem Games": [8652], "Polyphony Digital": [12, 26, 29, 30, 39, 198, 307], "Vanilla Ware": [2625, 8759], "Bitmap Brothers": [5753], "Zombie": [6174], "Adrenium": [2337, 4852, 8467, 10216], "Metro Graphics": [4823], "Appaloosa Interactive": [2463, 6204, 6400], "Juice Games": [2358, 2801, 3551, 4706, 5744, 10526], "WBIE": [2867, 4927], "Bec": [4808, 5300, 8256], "WinkySoft": [6559], "Team Soho": [265], "Barnhouse Effect": [1430, 7862], "Giants Software": [1570, 2303, 3621, 6330, 6605, 6786, 8527, 9953], "ArenaNet": [513, 8957, 9435, 9615, 10329], "Icon Games": [7728, 8553, 8873], "Phoenix Interactive Entertainment": [5184], "Blade Interactive": [2861, 8797, 8893, 9203, 10125], "Sidhe Interactive": [4171, 4260, 4392, 4712, 4781, 5617, 6934, 7965], "Buena Vista Games": [5604, 7816], "Imagineer": [8576], "Iron Lore Entertainment": [8522], "Indi": [7649], "Kodiak Interactive": [5172, 8015], "Next Level Games": [435, 848, 3706, 4258, 4521, 5458, 5491, 5844, 6292, 6751, 8217, 9047], "Full Fat": [3550, 6439, 10001], "DTP Entertainment": [8096, 8819, 9888, 9956, 10646], "Mere Mortals": [7071], "TopWare Interactive": [6390], "Harmonix Music Systems": [136, 313, 464, 490, 548, 550, 593, 613, 769, 846, 938, 1112, 1340, 1344, 1346, 1490, 1750, 1872, 2500, 2597, 3038, 3199, 3302, 3636, 3754, 3860, 4068, 4076, 4206, 4564, 4855, 4929, 4949, 5030, 5081, 5354, 5465, 5505, 5560, 5598, 5649, 6093, 6118, 6200, 6615, 6637, 6746, 6847, 7069, 7087, 7101, 8032, 8054, 8084, 8203, 8437], "Shiny Entertainment": [312, 1238, 2469, 2818, 2957, 3131, 3136, 4134, 4373], "Max Five": [8812], "2K Australia": [2097, 2432, 4312], "Magenta Software": [2655, 7074, 7899, 10122], "EA LA": [75, 134, 940, 1230, 1270, 2313, 2786, 2960, 3129, 3329, 3746, 4717, 7984, 8776, 9897], "Torus Games, Little Orbit": [9040, 9510, 9695, 10423, 10431], "Anchor Bay Entertainment": [7915], "Mass Media": [704, 1679, 2374, 2859, 3861, 4010, 4324, 4427, 6584, 7113, 8318, 8675, 9850], "Infogrames Sheffield": [10039], "MachineGames": [892, 2208, 3189, 3213, 3311, 3640, 6127, 7573], "Warthog": [2898, 4386, 4607, 5482, 5837, 6084, 7120, 7793, 7826, 8065, 9546], "TML-Studios": [10390], "Games Farm": [5588, 7709, 9643], "Alfa System": [7014, 8514, 8937, 10133], "Prope": [3558, 5853, 7497, 8362, 8443], "Harmonix Music Systems, Demiurge Studios": [3428, 3461], "Smack Down Productions": [4026, 4726], "Koolhaus Games": [7314, 7428], "Maximum Games": [3416], "Beep Industries": [6747], "Dancing Dots": [6616], "Land Ho!": [1803, 4439], "Hudson": [48, 462, 592, 879, 3086, 4685, 4744, 6536, 7681, 9099], "Big Blue Bubble Inc.": [6609, 7364], "Ivory Tower": [5150, 7325, 10058, 10081], "Bandai Namco Games, Artdink": [4803], "CyberConnect2, Racjin": [2076, 3212], "Turbine Inc.": [9959], "Arrowhead Game Studios": [9604], "Pyro Studios": [5341, 5717, 7033, 7090, 7990, 8392, 8953, 9062, 9838, 10101], "Hydravision": [5679, 6720, 8151, 8317, 9213], "4A Games": [2739, 3372, 3832, 4877, 5543], "Empire Oxford": [6930, 8766, 9906], "Larian Studios": [4925, 6517, 7989, 9638, 10182], "Sonic Powered": [8834], "Midway Studios - San Diego": [6857, 7217], "Sumo Digital": [364, 662, 1436, 1757, 2341, 3533, 3632, 3666, 3730, 3964, 8696, 8899, 10401], "CD Projekt Red Studio": [220, 1107, 1575, 1694, 2100, 4009, 8370], "Torus Games": [3455, 4859, 5361, 5626, 5912, 5987, 6342, 6658, 6678, 7197, 7686, 10285], "Black Bean Games": [10363], "Eighting, Genius Sonority Inc.": [2137], "Jack of All Games, eV Interactive": [7580], "Ubisoft Vancouver": [4562, 4919, 5704, 6113, 6819], "Acclaim Studios Manchester": [6813, 8536], "Game Arts, Seta Corporation": [6152], "DONTNOD Entertainment": [3495, 4033, 5718, 6523, 8493, 8902], "Leviathan Games": [8101], "N-Fusion Interactive Entertainment Corp.": [6085, 6706, 7726], "Take-Two Interactive": [3798, 3824, 4628, 4807, 5571, 6154, 6265, 6621, 6803, 6878, 7442, 7900], "Falcom": [5377, 6241, 6513], "Aqua Pacific": [7473], "Tecmo": [1447, 1502, 3100, 3763, 3889, 5284, 5498, 5872, 5994, 6296, 7165, 7232, 7448, 7530, 7738, 8254, 8304, 8440, 8774], "OfficeCreate": [366], "Day 1 Studios": [1318, 2726, 3178, 3194, 3781, 3917, 3957, 6005, 6116], "Keen Games": [4883, 5499], "Merscom LLC": [5434], "neo Software": [1212], "EA Canada, EA Vancouver": [3942, 4871], "BattleGoat Studios": [9310], "Fusionsphere Systems": [8971], "Square Enix, Tri-Ace": [1931, 2086], "Access Games": [4128, 4596, 6842, 8926], "Atari, Slightly Mad Studios, Atari SA": [9026], "Guildford Studio": [7029, 7045], "Colossal Order": [6373, 8643, 10491], "Blue Tea Games": [10405], "Cranberry Production": [8563], "GRIN": [2798, 3733, 3762, 3844, 4290, 4425], "Just Add Monsters": [4388], "Rage Software": [1786, 5174, 6198, 6965, 7355, 7394], "Starfish": [8123], "The Digital Lounge, Dino Dini": [9825], "Dreamworks Interactive": [417, 1560], "Ascaron Entertainment GmbH": [9011, 9264, 9928], "King of the Jungle": [10371, 10498], "Deadline Games": [7471, 9727], "Ubisoft Barcelona": [7931], "Flagship Studios": [9991], "SCE Japan Studio": [757, 1301, 2362, 3043, 4467, 4661, 5348, 5637, 6598, 9559], "Immersion Software & Graphics": [7137, 8625], "Human Head Studios": [4137, 4582, 6909], "Impressions Games": [9263, 9759], "Darkworks": [6003, 6960, 8331], "Asmik Ace Entertainment, Inc": [5968], "Eurocom Entertainment Software": [288, 296, 1484, 1855, 1947, 1949, 2054, 2179, 2308, 2425, 2614, 2653, 2918, 3170, 3237, 3388, 3598, 3760, 3795, 3932, 4351, 4485, 4492, 4747, 5084, 5253, 5429, 5630, 5708, 5752, 5814, 5915, 6016, 6244, 6354, 6372, 6475, 6527, 6869, 6899, 7310, 7382, 7399, 7583, 9598], "Storm City Games": [6062, 9475, 9543], "CI Games": [8551, 8928], "Tamsoft": [5053, 6076, 6155, 6639, 6870, 7417], "Unigine Corp, Russia": [9977], "Nerve Software": [2211, 3156], "Backbone Vancouver": [5160, 5764], "Frame Studios Interactive": [8809], "Tripwire Interactive": [6486, 8635], "Goshow": [8098], "h.a.n.d. Inc.": [897, 5266, 6359], "Avalon Style": [9119], "Splash Damage, The Coalition": [302], "Wildfire Studios": [4148], "Eutechnyx, Deep Silver": [8507, 8991], "Kojima Productions, Moby Dick Studio": [284, 2004, 2312, 5652], "Osiris Studios": [5208], "Kuju Entertainment": [3232, 3497, 3891, 4542, 6105, 6775, 7115, 7827, 8876, 9527, 9535, 10429], "Studio Gigante": [3176, 4461], "EA Vancouver": [609, 787], "Black Ops Entertainment": [1646, 2544, 2638, 4370, 6233, 6326, 6755, 6790], "Sandlot Games": [9622], "Mucky Foot Productions": [4187, 6502], "Simon & Schuster": [4263, 8524], "Mix Max": [6324, 7936], "Omega Force, Koei Tecmo Games": [2730], "Mindware Studios": [9708], "Eidos Montreal, Nixxes Software": [9346], "Little Orbit": [7642, 9294, 10340], "THQ Digital Studio Phoenix": [2698, 3106], "Game Machine Studios": [5293, 9829], "Evolution Games": [1866, 4964], "Eurocom Entertainment Software, Visceral Games": [3076], "Spidersoft, Spiders": [10375], "Eugen Systems": [2916, 4531, 4558, 10509], "THQ Australia": [6201, 6761], "Deep Silver, Keen Games": [7162], "2015": [4715], "Slant Six": [1171, 1259, 1962, 9104], "UFO Interactive, CyberPlanet Interactive Public Co., Ltd.": [10023], "Avalanche Software": [856, 982, 1295, 1550, 2285, 2389, 2458, 2648, 3105, 3476, 3868, 3956, 4393, 4500, 4597, 4764, 4853, 5290, 5584, 5782, 6117, 6423, 6511, 7175, 8008, 8031, 8920], "RedLynx": [3348, 4812, 9373], "THQ, 1C, 1C Company": [8602], "Ino-Co": [10264], "Housemarque": [7563], "Direct Action Games": [8010, 9636], "10tacle Studios, Fusionsphere Systems": [8349], "Conspiracy Entertainment": [8346, 9318], "Realtime Worlds": [744], "Deep Fried Entertainment": [7578], "Ludia Inc.": [1864, 2385, 3806, 4857, 6562, 6873, 6936, 7177], "Sucker Punch": [358, 389, 702, 712, 1219, 1845, 9247], "Humongous Entertainment": [2971, 6489, 6628, 8161, 8925, 9993], "Marvelous AQL": [3025], "NanaOn-Sha": [657, 6332, 8622], "Level 5": [131, 895, 928, 1561, 1628, 1826, 2356, 4620], "Endemol": [4074, 4527, 6867], "id Software, Raven Software": [2359, 2656, 8874], "Bandai": [2102, 2158, 2555, 6122, 7133, 7444, 7587, 8754, 8787, 9418, 10167], "Genius Sonority Inc.": [447, 864, 1174], "Rockstar Toronto": [299, 1749, 2778, 2796, 2802, 2900, 4366], "Koei/Inis": [7184, 8837], "Mad Doc Software, Rockstar Vancouver": [1419, 9632], "Valhalla Game Studios": [8395], "Treyarch, Shaba Games": [4639, 4752, 5251, 9952], "SScholastic Media": [5990], "Danger Close": [1006, 1292, 3990], "Phantagram": [4094, 6132], "Celeris": [9482], "Q Entertainment": [3260, 5102, 7767], "5000ft": [8014, 9399], "Team6 Game Studios": [9530], "Sting": [6638, 6674, 6919, 7844, 7942], "Rhino Studios": [5149], "Pipe Dream Interactive": [2664, 6206], "EA Mythic": [9725], "THQ": [480, 730, 1052, 1553, 1963, 2416, 2721, 2766, 2930, 3264, 3420, 3460, 3886, 4304, 4418, 4423, 4568, 4598, 4920, 4979, 5103, 5271, 5451, 5477, 5493, 5528, 5677, 5726, 5769, 5825, 5838, 6086, 6164, 6270, 6977, 7005, 7252, 7529, 7646, 8882, 10055], "Magic Pockets": [1711], "EA Black Box": [64, 426, 605, 612, 628, 1380, 1822, 2112, 3712, 5761, 7911], "Visceral Games": [580, 921, 999, 1227, 1387, 1539, 1564, 1655, 3419, 4024, 4363, 4456, 4660, 5446, 6448], "Guerilla Cambridge": [7075], "Headstrong Games": [1811, 4969, 10543], "Playground Games": [1022, 1391], "Wideload Games Inc.": [3195, 6948, 8512, 8688], "Tri-Ace": [765, 1364, 1878, 2053, 2150, 2282, 3050, 3982, 9160], "1C:Ino-Co": [10040, 10210], "Logris Games": [10252], "TDK Mediactive": [10454], "Tri-Crescendo": [3265, 3745, 4039], "Smart Bomb Interactive": [3959, 7702, 9826], "Ubisoft Bulgaria": [6286, 10358], "Nex Entertainment": [1228, 1836, 2759, 7418, 8402], "SCEA Sports Studio": [2789], "Lab Rats Games": [2397, 8949], "Her Interactive": [6246, 9331], "SNK": [6952, 7160, 9539, 9811], "Jet Black Games": [5037, 5415], "Confounding Factor": [9420], "Double Helix Games": [298, 1188, 3196, 3616, 4281, 4906, 4938, 5151, 5245, 5384, 5629, 5930, 6301, 6349, 6632, 7479, 7987, 8547, 8558, 8863, 9078], "Nintendo, Nintendo Software Technology": [10490], "Hit Maker": [7524], "The Game Factory": [7432], "WXP": [2745, 2788, 7482], "Certain Affinity": [272], "5TH Cell": [3740, 7228], "Re-Logic": [6285], "Open Sesame": [3699], "DMi Games": [5933], "SCE/WWS, Media Molecule": [105], "Blueside": [3705], "Propaganda Games": [2022, 2226, 3386, 4189, 8195, 10316], "Farsight Studios, Crave": [3201], "Atari, Transmission Games, Atari SA": [6056], "Telltale Games": [4435, 5135, 5235, 5658, 5763, 5908, 6088, 7537, 7913, 9098, 9499, 9917, 10128], "Milestone, Milestone S.r.l": [7891, 10319], "Subterranean Games": [10359], "Intelligent Systems": [242, 368, 529, 2741, 2961], "Sonic Team": [350, 362, 405, 443, 563, 606, 790, 855, 1154, 1279, 1373, 1482, 1529, 1581, 1658, 1681, 1683, 1703, 1971, 2447, 2897, 3029, 3584, 4603, 4718, 5308, 5537, 5615, 5750, 5935, 6583, 6808, 6855, 7643, 7863, 10333], "Infinite Interactive": [5099, 6732, 6824], "WildTangent": [3842], "Pterodon": [10049], "Fox Interactive": [257, 1442], "Paprikari": [8996], "D3Publisher": [4003, 5621, 5899], "Crystal Dynamics, Nixxes Software": [1473, 3870, 6778], "Haemimont": [3862, 4147, 4547, 5131, 6871, 7167, 7823, 8470, 8901, 9796, 10307, 10549], "Oberon Media": [10143, 10617], "Liquid Entertainment": [6314, 6346], "Totally Games": [3007, 4677, 8344], "Bluepoint Games": [163, 433, 1049, 6552, 8367, 9082], "GenePool": [2316, 5291, 6779], "Human Soft, Ivolgamus": [3152, 6849], "HotGen": [6949, 10361], "Stormregion": [9470, 10343], "Codemasters Birmingham": [1075, 1740, 2717, 3432, 5045, 7341, 8535], "Omiya Soft, Jamsworks": [6021], "SouthPeak Games": [8814, 8852], "Digital Illusions": [2615, 2641, 3219, 3462, 3802, 4198, 4494, 5894, 6711, 7749, 9586, 9664], "Neversoft Entertainment, Underground Development": [4259], "EA Games": [301, 1309, 1361, 1416, 1491, 2534, 3053, 3097, 3679, 4255, 4309, 4520, 4688, 4690, 4898, 4937, 5157, 5555, 8446, 8992, 9174], "Steel Monkeys": [1090, 4839], "Respawn Entertainment": [352, 2002, 2589, 2626, 7752], "Digital Leisure Inc.": [7683], "Criterion Games": [394, 415, 551, 640, 1056, 1111, 1175, 1691, 1807, 2027, 2785, 2928, 3380, 3701, 4207, 4841, 4988, 6111, 6673, 7412], "Factor 5, SCE/WWS": [2862], "Crispy's": [4658], "Rare Ltd.": [97, 678, 839, 1927, 1957, 3063, 3923, 6282], "Empty Clip Studios": [10427], "Spiders": [5462, 8332, 9613], "Doublesix": [8166], "Illusion Softworks": [2157, 4985, 8895], "SimBin": [5792, 9358, 9490, 9828, 10645], "KCEJ": [100, 101, 192, 2012, 2380, 2821, 3399, 7653, 9171], "JGI Entertainment": [5009], "Atomic Planet Entertainment, Mud Duck Productions": [9729], "Magic Pixel Games": [4994], "Zoo Games": [3526, 4104, 5536, 5585, 5939, 8045, 8201, 8251, 8327, 8724, 9769], "Rare Ltd., BigPark": [507], "Carapace": [8741], "Coffee Stain Studios": [10475], "City Interactive, Deck 13": [2836, 5124, 9492], "Reloaded Productions, Reloaded Games Inc.": [9172], "Ivolgamus": [7291], "Visual Impact": [9377], "Swordfish Studios": [5201, 5542, 6945], "MTO": [2816], "EA DICE": [63, 66, 207, 259, 277, 279, 280, 353, 396, 526, 621, 969, 1060, 1082, 1278, 1323, 2108, 3644, 3857, 5186, 5966, 8264, 8521, 9640], "Overkill Software": [2580, 3295, 8728], "SEGA Racing Studio": [2364, 3171, 10567], "Blue Tongue": [2944, 5028], "Project Aces": [1495, 2040, 2965], "SCEE London Studio": [723, 980, 1050, 1327, 1357, 1530, 1629, 1891, 2342, 2834, 3102, 4360, 5774, 5896, 5956, 6366, 6465, 6518, 6914, 7332], "Toolbox Design": [1787], "Zindagi Games": [4429], "Nd Cube": [47, 319, 745, 9685], "Ubisoft Shanghai/Paris": [1389], "TT Fusion": [1469, 2166, 2637, 3379, 5858, 8494], "Kojima Productions": [102, 1149, 2520, 4333, 6341, 7879, 9117, 10629, 10640], "Crytek": [1031, 1071, 1125, 1692, 1779, 2044, 2115, 2371, 6776, 8808, 10035], "Software Creations": [5508], "Compulsion Games": [10311], "City Interactive": [1286, 1932, 2986, 3961, 4012, 5306, 6095, 7782, 9660], "Boxed Dream": [9810], "Big Ant Studios": [5700, 6760, 8104, 9737, 9757, 10207, 10341, 10557], "Mercury Steam, Alchemic Productions": [4096, 5378, 10559], "Activision, Activision Blizzard": [7494], "Remedy Entertainment": [1085, 2311, 2661, 8219, 9603, 9905, 10277], "Rocksteady Studios": [114, 156, 191, 222, 278, 946, 2800, 4047, 4212, 8441, 10066], "Transmission Games": [6457], "Doki Denki": [7317, 8626], "Inevitable Entertainment": [2754, 5799, 7065], "Nintendo, Camelot Software Planning": [3209], "Griptonite Games": [3126, 6892, 6973, 7104], "KCEO": [3749, 8352, 8691, 9154, 9343, 10132], "Destination Software": [3850, 4089, 8394], "Relic": [2633, 3070, 3198, 3900, 4757, 5313, 7797, 8765, 8854, 9013, 9044, 9441, 9916, 10378], "Wide Games": [7676], "Deep Space": [2683], "369 Interactive": [6866], "Ensemble Studios": [428, 3672, 6426, 7416, 7641, 9034, 9635], "Roxor Games": [7941], "Volition Inc., Reactor Zero": [9341], "KCEA": [9987, 10036], "2D Boy": [9218], "Microsoft Game Studios": [1445, 1519, 2418, 2455, 3317, 4088, 5775, 5843, 7044, 7422, 8136, 9513, 10146], "Blue Fang Games": [2446, 4667, 8404, 8433, 9504], "PopCap": [1395, 2177, 2272, 2422, 2963, 3006, 4577, 5424, 6316, 6433, 7693, 8684, 8717, 8749, 9025, 9359, 9761, 9821, 9844, 10138, 10139, 10624], "Compile Heart, GCREST": [6108], "Best Way": [9061, 9396], "SCEA San Diego Studios": [1622, 1648, 1654, 2046, 2092, 2096, 2159, 2538, 3290, 3365, 3602, 3965, 4117, 5940, 6163, 6530, 6563, 6617], "Midway Studios - Los Angeles": [2169, 4136], "KCET": [231, 346, 363, 568, 854, 1140, 1540, 1606, 1980, 2121, 2270, 2561, 2890, 3203, 3652, 4419, 5194, 5489, 5716, 6011, 7164, 7565, 7802, 8234, 10569], "Compile Heart": [4967, 5402, 5612, 6725, 7995, 8079, 8102, 8282, 9714, 10517], "The Workshop": [4254], "SoftMax": [5112], "Ubisoft, FunHouse": [8128], "Racjin": [2652, 2956, 4504, 5936, 7626, 7849], "Blue Byte, Related Designs": [991, 3661], "Success": [7955, 8036], "TT Games": [543, 695, 814, 843, 1028, 1143, 1198, 1360, 1433, 1441, 1636, 1640, 1696, 1712, 1721, 1773, 1799, 2043, 2047, 2072, 2153, 2225, 2277, 2310, 2478, 2781, 2830, 3116, 3137, 3167, 3289, 3854, 4108, 4250, 4510, 4532, 4908, 5069, 5125, 5890, 6019, 6170, 6257, 6783, 6868, 8301, 8308, 8777, 9132, 9623], "Touchdown Entertainment": [9957], "Coyote Console": [8113, 8855], "Disney Interactive Studios": [2344, 2514, 2909, 4412, 5000, 5924, 6748], "Visual Sciences": [6895], "Planet Moon Studios": [989, 2006, 6690], "System 3": [6065, 9374, 10021, 10309], "SunSoft": [3977], "Paradox Development": [2093, 2450, 3033, 4403, 5918, 6161, 6851, 7046], "The Behemoth": [7264, 7446], "IR Gurus Interactive Ltd.": [6591], "Digital Fiction": [5180], "United Front Games": [1331, 1452, 1759, 6709], "Chris Sawyer": [1177, 8918], "3DO": [3703, 3759, 4228, 4821, 5776, 5783, 5828, 5882, 6146, 6323, 6533, 6640, 7794, 7977, 8409, 8644, 9017], "Rockstar North": [8, 9, 10, 11, 23, 28, 32, 115, 637, 1138, 1265, 1547, 5459, 9091], "Rockstar San Diego": [84, 92, 470, 501, 721, 880, 973, 1160, 1275, 1312, 1410, 2005, 2033, 2710, 2902, 5310, 5540, 5681, 6528, 7763], "Twelve Games": [9639], "EA Sports, EA Vancouver": [58, 420, 2050, 3650, 6875], "Awesome Play Ltd.": [8024], "Monolith Productions": [349, 1057, 2368, 2815, 3054, 3403, 3594, 3810, 6393, 7975], "iWin": [10447], "Nordcurrent": [9560], "Bizarre Creations": [570, 2105, 2163, 2515, 3040, 3952, 4508, 4951, 6345, 8338, 10103], "Vivendi Games": [5452, 7349, 7809], "Replay Studios, ML Enterprises": [5766], "Black Box": [486, 573, 622, 1048, 1874, 2628, 3341, 3747, 4277, 4470, 6801, 6963, 7912, 8152, 8550, 8778, 8802], "Kuusou Kagaku": [2925, 6550], "Taito Corporation, 505 Games": [8733], "Capcom, QLOC": [8986, 9830], "Akella": [4317, 10202], "Still Alive Studios": [9550], "Tetris Online, Inc": [2660], "Maxis": [238, 328, 330, 345, 472, 562, 655, 705, 735, 794, 997, 1144, 1232, 1272, 1889, 2266, 2630, 2848, 3055, 3523, 3534, 3905, 3948, 4241, 4261, 4334, 4545, 4751, 5096, 6897, 7204, 7877, 8048, 8119, 8480, 8832, 8999, 9002, 9102, 9351, 9626, 9996, 10038, 10257], "RED Entertainment, Compile Heart": [7251], "Aspect": [2675], "InXile Entertainment": [4714, 5143, 5175, 7166, 7262, 8618, 8650, 9785], "Amusement Vision": [918, 963, 1366, 1893, 2284, 8610], "Microids": [7182, 7978, 8985, 9526, 9529, 9653, 9860, 10238, 10251, 10437], "Konami": [179, 209, 252, 483, 519, 539, 555, 597, 708, 746, 862, 865, 872, 903, 1141, 1191, 1243, 1406, 1456, 1587, 1862, 1881, 1920, 1924, 2016, 2202, 2435, 2572, 2878, 2915, 2927, 3090, 3184, 3233, 3376, 3405, 3483, 3530, 3675, 3811, 3902, 3922, 4020, 4034, 4045, 4065, 4179, 4237, 4248, 4289, 4325, 4629, 4914, 5063, 5223, 5231, 5234, 5265, 5304, 5512, 5524, 5569, 5623, 5738, 5743, 5770, 6002, 6140, 6153, 6157, 6306, 6362, 6379, 6494, 6549, 6554, 6557, 6575, 6624, 6859, 6872, 6946, 6978, 7108, 7169, 7285, 7337, 7426, 7438, 7504, 7677, 7680, 7715, 7748, 7773, 7892, 7898, 8066, 8103, 8172, 8279, 8353, 8417, 8500, 8560, 8683, 8825, 8914, 8974, 9073, 9195, 9219, 9266, 9523, 9540, 9711, 9840, 9936, 10374, 10389, 10550, 10554, 10616], "Namco": [68, 107, 215, 229, 282, 315, 602, 604, 770, 866, 919, 929, 964, 967, 1051, 1185, 1293, 1359, 1394, 1407, 1511, 1722, 1873, 2073, 2087, 2144, 2426, 2579, 2761, 2824, 2880, 2983, 2987, 3570, 3721, 3881, 3950, 4371, 4528, 4843, 5059, 5397, 5408, 5791, 6351, 6687, 6771, 7030, 7138, 7191, 7594, 7886, 7917, 8133, 9191], "Vigil Games": [1431, 1813, 1916, 6139, 6144, 6184, 10076], "Slightly Mad Studios": [422, 659, 1371, 4618, 6691, 8432], "Papaya Studios": [675, 1065, 3250, 4268, 4402, 4816, 5004, 5058, 5061, 5128, 5703, 6959, 8543, 8738], "Zoom": [4432], "Hasbro Interactive": [4901], "PopTop Software": [9038, 9225], "Bright Future GmbH": [8835], "Ubisoft Barcelona, Ubisoft Reflections": [3071], "iNiS": [1953, 2703, 4028, 5722], "Dracue": [9697], "Cerasus Media": [9329], "Crafts & Meister": [3684], "Fusionsphere Systems, Animation Arts": [9223], "Tectonic Studios": [7672], "Sega Studios San Francisco": [3587, 4490], "Scientifically Proven": [7360, 7907], "Sacnoth": [4367], "Ubisoft, Ludia Inc.": [5590], "KCE Studios": [1643, 3205, 5400, 5651, 6979], "Animation Arts": [6913], "Avalanche Studios": [690, 741, 853, 1688, 6311, 6402, 6697, 10194, 10289], "Yoostar Entertainment Group": [8040], "Mad Doc Software": [5647, 9101, 9462, 10248], "343 Industries": [38, 171, 308, 487], "Point of View": [2829, 3215, 3263, 3517, 3638, 3761, 3919, 3933, 4246, 5338, 5638, 5859, 6074, 6343, 6418, 7055, 7397, 7564, 7590, 7973, 8155, 8879, 9250, 9820, 9940, 10262], "Monolith Soft": [749, 1673, 1819, 3734, 4489, 8064], "Alawar Entertainment, Inc, Alawar Entertainment": [9015], "Jester Interactive": [2117, 3544, 6107, 9233], "Marvelous": [1910, 4832, 4861, 5624], "Smilebit": [4584, 5256, 5897, 8670], "Dovetail Games": [9140], "Cyan Worlds": [473, 10112], "Radical Entertainment": [1110, 1189, 1245, 1422, 1918, 2032, 2724, 2758, 2913, 2967, 3062, 3160, 3321, 3408, 3698, 3949, 4107, 4848, 4959, 5090, 5154, 5409, 5534, 5854, 5983, 6234, 6352, 6681, 6806, 7091, 7220, 8025, 8706, 9183, 10116, 10432], "Societe Pollene": [10521], "SCEE, Zoe Mode": [197], "FAKT Software": [9803], "Arkane Studios": [767, 905, 2328, 5117, 6787, 8701, 9319], "Humagade": [4188], "Robomodo": [2431, 2493, 2736, 4411, 4656, 5283, 6812, 8082, 8391], "Volition Inc.": [335, 402, 466, 556, 654, 791, 812, 933, 1168, 1770, 2037, 2842, 2865, 3162, 3613, 3656, 5219, 5595, 7617, 8745, 10592], "FUN Labs": [2444, 3528, 3670, 3818, 4183, 4247, 4526, 4589, 4819, 4971, 5082, 5224, 5392, 5547, 5689, 5730, 5784, 5801, 5944, 5985, 6042, 6099, 6398, 6556, 6590, 6623, 6796, 6856, 6896, 6990, 7094, 7158, 7807, 7847, 8237, 8364, 8844, 8853, 9267, 9295], "Climax Group, Climax Studios": [3077, 4732, 6480, 9164, 9720], "BigPark": [988], "Headup Games": [9457], "Neon Studios": [8624], "Pivotal Games": [878, 2771, 5057, 5437, 5478, 5531, 5574, 7230, 7921, 8337, 10486], "Firebrand Games": [4474, 4999, 5514, 5641, 6788, 7329], "Idol Minds": [3414, 3966, 4209, 4893], "Mad Catz": [5420, 7971], "Monumental Games": [5087, 5849, 5875, 8363], "EA Sports": [45, 99, 139, 148, 170, 189, 203, 255, 270, 304, 306, 327, 360, 406, 430, 477, 538, 554, 558, 608, 616, 680, 683, 696, 740, 773, 775, 797, 803, 826, 833, 873, 876, 877, 900, 934, 954, 972, 983, 984, 1023, 1083, 1113, 1167, 1190, 1192, 1215, 1239, 1280, 1356, 1398, 1444, 1448, 1521, 1534, 1545, 1546, 1551, 1569, 1611, 1623, 1625, 1685, 1702, 1716, 1717, 1771, 1798, 1839, 1841, 1883, 1915, 1943, 1987, 2069, 2140, 2155, 2194, 2205, 2354, 2366, 2387, 2440, 2452, 2482, 2503, 2504, 2574, 2588, 2665, 2668, 2737, 2817, 2826, 2875, 2882, 3024, 3083, 3111, 3140, 3150, 3218, 3282, 3313, 3322, 3383, 3409, 3424, 3464, 3630, 3751, 3991, 4060, 4170, 4176, 4365, 4501, 4505, 4509, 4534, 4536, 4676, 4872, 4905, 4936, 4986, 5018, 5071, 5121, 5254, 5259, 5277, 5343, 5347, 5360, 5702, 5712, 5720, 5771, 5812, 5815, 5959, 6077, 6082, 6119, 6120, 6171, 6183, 6481, 6538, 6886, 7080, 7109, 7221, 7651, 8134, 8257, 8505, 8775, 8826, 9394, 9609], "Red Storm Entertainment": [733, 1047, 1276, 1758, 3603, 6268, 7663], "Bionic Games": [7041], "Runecraft": [1756, 3276, 8838, 10520], "Hello Games": [777], "Legacy Interactive": [6455, 8548, 9532], "SolWorks": [4970], "Amanita Design": [7049, 9564], "Indies Zero": [4421], "KnowWonder": [8491, 9187, 10441], "SCE Santa Monica": [153, 175, 208, 531, 4027], "NaturalMotion": [5676, 5813], "Ubisoft": [34, 40, 77, 86, 122, 244, 261, 300, 373, 508, 534, 537, 541, 569, 620, 623, 648, 810, 886, 1133, 1254, 1283, 1332, 1334, 1499, 1520, 1596, 1620, 1641, 1747, 1832, 1960, 2019, 2074, 2239, 2287, 2306, 2390, 2454, 2461, 2462, 2480, 2557, 2584, 2613, 2640, 2684, 2779, 2892, 3132, 3227, 3305, 3354, 3391, 3400, 3418, 3459, 3478, 3606, 3677, 3694, 3696, 3757, 3783, 3800, 4022, 4051, 4056, 4168, 4225, 4227, 4257, 4344, 4357, 4359, 4552, 4588, 4705, 4854, 5426, 5466, 5474, 5486, 5765, 5785, 6001, 6214, 6236, 6442, 6468, 6534, 6564, 6567, 6721, 6728, 6764, 6898, 6984, 6986, 7064, 7073, 7149, 7222, 7293, 7309, 7747, 7838, 7869, 7875, 7893, 7956, 8041, 8087, 8182, 8213, 8615, 8627, 8676, 8994, 9443, 9459, 9650, 10024, 10190, 10209, 10364], "Bethesda Softworks": [180, 372, 1103, 4678, 4912, 5376, 5481, 7243, 7659, 8385, 10290], "Rockstar Leeds": [264, 1552, 4769], "Ruffian Games": [1339], "Omega Force": [575, 681, 1024, 1059, 1200, 1516, 1677, 1778, 1791, 1835, 2273, 2404, 2419, 2457, 2599, 2947, 3091, 3175, 3249, 3878, 3924, 3928, 4105, 4235, 4270, 4284, 4383, 4610, 4642, 4683, 4828, 4849, 4902, 4946, 4987, 5428, 5461, 5507, 5591, 5888, 5997, 5998, 6091, 6130, 6408, 6429, 6641, 6669, 6858, 6943, 7369, 7407, 7546, 7765, 7866, 7934, 8075, 8449, 8454, 8561, 8645, 8816, 9070, 9115, 9515, 9979], "Hellbent Games": [7561], "Oddworld Inhabitants": [1184, 1525, 2065, 4646], "Bluehole Studio": [3394], "Bunkasha Publishing": [2604], "Jellyvision": [641, 7244], "Rockstar Vancouver": [1618], "Surreal Software": [1231, 3395, 4653, 5088, 5773, 7577], "Bungie": [36, 652, 653, 845, 3725, 4882, 6782], "Lost Toys": [5732, 9283, 10181], "Yacht Club Games": [7356, 7710], "Isopod Labs": [7492, 7935, 8039], "Page 44 Studios": [1415, 1792, 2242, 2370, 3595, 4756, 4913, 4918, 5797, 6375, 7440], "Voxler": [9327], "Beyond Games": [3052, 6983], "Black Isle Studios": [2186, 4675, 9277, 10552], "n-Space": [3454, 3877, 4032, 5015, 5191, 6219, 7908], "Teyon": [5636, 7216], "Takara": [4431, 5286, 7490, 9705], "Factor 5": [663, 1894], "O-Games": [8496], "Brainbox Games": [8271], "Neversoft Entertainment, BudCat": [144], "THQ, Yuke's": [1156], "Lexis Numerique, Virtual Toys": [4637, 5164], "Hudson, NATSUME ATARI Inc.": [5032], "Machatin, Inc.": [2827, 4652], "Aqua Plus": [6158], "Gorilla Games": [1911, 6597], "7 Studios": [2942, 3477, 3485, 3548, 4525, 4775, 4875, 5046, 6595, 7542, 8883], "ZootFly": [4722, 5268], "Hypnos Entertainment": [2182], "Ryu ga Gotoku Studios": [1337, 1588, 2451, 2502, 6051], "XPEC Entertainment Inc.": [7131], "Big Time Software": [9392], "Various": [7042, 9507, 9862, 9946, 10511], "Creat Studios": [3349, 5713, 6129, 6910, 8026, 8307, 8772, 8783], "Turn 10": [113, 166, 211, 549, 717], "InterServ International": [9872], "Gusto Games": [4546, 7002, 8012, 10522], "Inland Productions": [3797, 6881], "Vicarious Visions, Neversoft Entertainment": [1571], "Artificial Mind and Movement, Polygon Magic": [1965], "Paradigm Entertainment": [802, 2326, 2814, 3439, 3930, 4400, 4522, 5883, 6133, 6570, 8355, 8849, 9891, 10260], "Mistwalker, Artoon": [1661, 2292], "Red Tribe, Brash Entertainment": [7536], "5pb": [8686, 9035], "Media Molecule": [287, 4593], "Eden Studios": [1959, 2988, 4093, 5965, 6551, 8519, 9851, 10240, 10556], "VU Games": [2810, 4948, 7121], "GlyphX Games": [6651], "Ubisoft Annecy": [5340], "Ubisoft Quebec": [289, 1119, 2421, 3829, 4931, 5218, 5633, 6357, 6845, 8492, 10064], "Stealth Studios": [5132, 8487], "Cohort Studios": [3925], "SingleTrac": [8456], "CyberConnect2": [1150, 1225, 1317, 1409, 1624, 1939, 2207, 2442, 2560, 2593, 2885, 3127, 3255, 3285, 3504, 4210, 4860, 5134, 9300], "Ascaron Entertainment GmbH, Ascaron Entertainment": [2434, 2749, 8410], "Cat Daddy Games": [212, 883, 2488, 4124, 8406], "MicroProse, n-Space": [5333], "Cinemaware": [5581], "Black Lantern Studios": [3664, 4331, 5808, 8649, 8866, 9894], "Design Factory": [8478], "Codemasters": [1021, 1234, 1362, 1435, 1437, 1463, 1527, 1635, 1676, 1684, 1768, 1769, 1899, 2101, 2109, 2241, 2952, 3682, 3720, 3728, 4061, 4113, 4221, 4395, 4471, 4487, 4495, 4805, 4958, 5587, 5692, 5747, 6141, 6279, 6704, 6809, 7200, 7574, 7682, 7835, 8055, 8236, 8614, 8630, 8648, 8727, 8779, 8907, 9039, 9121, 9133, 9254, 9372, 9682, 9804, 9854, 9998, 10276, 10545], "Cattle Call": [3791, 8265, 8472], "Hitmaker": [5309, 8118, 8523], "Gameloft": [2259], "Strawdog Studios": [9867], "Headup Games, Crenetic Studios": [10043], "IR Gurus": [4307, 7367, 10072], "UDS": [1638, 3778, 6218, 7953, 8871], "Gaming Minds Studios": [5350, 7938, 8739, 9072], "Saber Interactive": [3413, 6040, 8143, 8431, 10477, 10505], "HB Studios Multimedia": [808, 4111, 4434, 5129, 6243, 6916, 7437, 7513, 7522, 7619, 7699, 8473, 8479, 8764, 9383, 9412, 9445, 9834, 10177, 10275, 10548], "Nikitova Games": [8285], "Pam Development": [2532, 2617, 2635, 3130, 5841, 7148], "Outrage Games": [6614, 6745, 8735], "Techland": [494, 523, 587, 1128, 1741, 1942, 2453, 2460, 4329, 4567, 5137, 5393, 5667, 6437, 6843, 7281, 8038, 8608, 9339, 10353], "Z-Axis, Ltd.": [1037, 1443, 3421, 3856, 3866, 4446, 4478, 5405, 5820, 6274, 7067, 7225, 8240, 8242, 8475], "Deep Red": [10077], "Midway": [458, 459, 626, 651, 669, 671, 811, 961, 1288, 1414, 1574, 1713, 1846, 1865, 1871, 1988, 2498, 2774, 2777, 2889, 3056, 3065, 3314, 3448, 3489, 4230, 4345, 4409, 4424, 5017, 5257, 5270, 5602, 5650, 5693, 5819, 5919, 5937, 6050, 6288, 6466, 6487, 6679, 6999, 7147, 7207, 7427, 7705, 7883, 8135, 8162, 8490, 8585, 8987, 9403, 9440, 9835, 10481], "Magix": [4184], "Nfusion": [6677], "Jaleco Entertainment": [5824, 6593, 7812, 8815, 10140, 10170], "Acclaim": [1109, 1821, 2119, 2705, 2980, 3629, 3962, 4085, 4238, 4669, 4947, 5113, 5122, 5914, 5996, 6121, 6194, 6240, 6464, 6485, 6633, 6635, 6689, 6785, 6837, 6844, 6971, 7155, 7890, 8345, 8545, 8955], "Black Sea Studios": [9456, 10086], "Boston Animation": [10524], "Good Science Studio": [6], "Paradox Interactive": [9668, 9889, 10259], "Autumn Moon": [9750, 10255], "Blizzard North": [1428, 6576], "EA Tiburon": [129, 168, 371, 377, 411, 414, 440, 445, 448, 491, 497, 500, 530, 667, 714, 764, 837, 847, 941, 998, 1000, 1013, 1365, 1372, 1379, 1382, 1408, 1489, 1543, 1548, 1614, 1645, 1734, 1755, 1810, 1828, 1833, 1884, 1929, 1936, 2095, 2099, 2111, 2134, 2146, 2237, 2288, 2290, 2300, 2386, 2518, 2536, 2575, 2627, 2776, 2828, 2833, 2863, 2931, 2932, 2992, 3010, 3138, 3145, 3244, 3646, 3690, 3709, 3711, 3813, 3840, 3859, 3953, 4313, 4352, 4507, 4590, 4634, 4923, 4982, 5010, 5399, 5758, 6254, 6336, 6826, 6911, 6915, 6932, 7255, 7896, 8973, 10386], "B-Alive": [7719], "id Software, Nerve Software": [2135], "Frozenbyte, Inc.": [9200, 10601], "Visual Concepts": [228, 342, 427, 429, 450, 465, 468, 506, 571, 576, 585, 674, 716, 763, 830, 834, 857, 978, 1080, 1096, 1147, 1214, 1369, 1440, 1480, 1544, 1577, 1600, 1678, 1723, 1744, 1796, 1820, 1827, 2049, 2415, 2456, 2658, 2693, 2747, 2870, 2926, 2953, 3157, 3449, 3453, 3484, 3622, 3687, 3695, 3772, 3784, 3845, 3904, 4082, 4524, 4572, 4576, 4605, 4981, 4983, 5138, 5334, 5335, 5445, 5527, 5594, 5755, 5767, 5811, 5957, 6052, 6081, 6106, 6124, 6189, 6211, 6420, 6524, 6542, 6661, 6833, 6928, 7761, 8275, 8740, 8995, 9495, 10324], "Mistwalker": [1686], "Blitz Games Studios": [1714, 2283, 2858, 3064, 3267, 3466, 6714, 7163, 7233], "Koei": [1591, 3101, 4099, 4219, 4328, 6098, 6540, 7061, 7476, 7540, 7569, 7581, 7605, 7756, 7924, 7985, 8005, 8051, 8090, 8253, 8280, 8780, 9989], "Ubisoft Toronto": [1542, 1608, 5570, 6853], "Obsidian Entertainment": [210, 322, 1043, 1266, 1649, 1650, 3310, 3573, 3614, 3727, 5523, 5798, 9276, 9721, 10088, 10356], "SCEA": [1116, 1633, 2103, 3113, 3410, 3771, 4566, 5035, 6226, 10144], "Tecmo, Ntreev Soft": [5083, 6957], "Wicked Witch Software": [9008, 9601, 9772, 10614], "Spike Chunsoft": [3830, 8044, 8277], "Data Design Interactive": [4788, 5106, 6828, 7499, 7746, 7937, 8138, 8628, 8822, 8988, 9647, 9671, 9818, 10154, 10256], "Hudson Entertainment": [6012, 7039, 7539, 8438], "SCEI": [686, 836, 8366], "Monster Games Inc.": [2467, 2553, 2790, 3554, 4644, 4944, 5298, 7487, 7567], "SCEJ": [3030, 3934, 8131], "Melesta": [9892], "Artefacts Studio": [1126, 9981], "Inti Creates": [4062, 8589, 9518, 10034], "Team Ninja, Tecmo": [1498], "Atomic Motion": [7415, 10153], "Artificial Mind and Movement": [2088, 2420, 2523, 2632, 2712, 2940, 3286, 3458, 3475, 3655, 3998, 4101, 4631, 4680, 4692, 4778, 6143, 6294, 6312, 6395, 6461, 6737, 7229, 7421, 7595, 8526, 8976, 9180, 9208, 9716, 9718, 9877, 10130, 10551], "Terminal Reality, 4mm Games": [3999, 4021, 4262], "Free Radical Design": [1524, 2160, 2323, 3251, 3293, 4830, 5986, 6309, 7795, 8052, 8679], "Nitro Games": [9415, 9512, 10160], "Incinerator Games": [1532, 2527, 2797, 2948, 3074, 5644, 6135], "Mediascape, CUBETYPE": [9907], "Toka": [7814], "WideScreen Games": [5342, 6839, 10157], "Egosoft": [7850, 9648], "Bam Entertainment": [2689, 6104, 7339, 7933], "Media Molecule, United Front Games": [1765], "Sony Bend": [1986, 2820, 4398, 8426], "EA Chicago": [804, 881, 959, 3323, 3875, 3969], "Monolith Soft, Namco Bandai Games": [7218], "Eidos Montreal": [1039, 1042, 3648, 5866], "Nixxes Software": [1166, 2526, 4097, 7637, 7840, 9244, 9982, 10148, 10599], "Eutechnyx": [1824, 2770, 3515, 4202, 4293, 4519, 5068, 5072, 5432, 5440, 6403, 6752, 6980, 7068, 7103, 7196, 7439, 7667, 7778, 7979, 8420, 8729, 9170, 10283], "Sand Grain Studios": [995, 1264, 1972, 2636, 3369, 3593, 3700, 3805, 4459, 6356, 6905, 7141], "Cyber Planet": [9654], "EA Seattle": [1860, 1904], "LucasArts, BioWare": [348], "Big Red Software": [10613], "Pacific Century Cyber Works": [4574], "Genki, Kojima Productions": [6224], "Alpha Unit": [10558], "Enigma Software Productions": [9972], "Deep Silver": [5867, 5928, 8646, 9588, 9688, 9885, 9935], "Vicarious Visions": [165, 254, 635, 889, 890, 1073, 1092, 1142, 1488, 1556, 1690, 1705, 2051, 2543, 2997, 3037, 3154, 3340, 3519, 3586, 3681, 3726, 4109, 4118, 4151, 4162, 4641, 4822, 4954, 6096, 9898], "Strangelite": [10067], "MagicWand": [2376, 8192, 9293], "Lucky Chicken": [4858, 6302, 9920, 10351], "Coldwood Interactive": [2524, 7154, 9161], "Silicon Knights": [1935, 3087, 3253, 4897, 4910, 7302], "Attention Software": [6626], "Collision Studios": [2645, 4773, 7610, 8035, 8168, 8435, 8439, 9122], "EA Redwood Shores": [267, 511, 625, 823, 920, 1016, 1737, 1922, 2028, 2089, 2315, 2497, 2904, 3005, 3088, 3098, 3364, 3465, 3742, 5603, 6126, 9625], "Lead Pursuit": [9812], "Lionhead Studios": [137, 190, 4100, 4381, 8116, 9136], "LucasArts": [400, 546, 736, 936, 985, 1376, 2143, 2222, 2920, 4441, 4608, 5403, 6484, 7174, 7694, 7964, 8708, 9474], "2K Czech": [893, 945, 2184, 3444, 3529], "Anchor": [2649, 2678, 4231], "Lucas Learning": [5952], "Monkey Bar Games": [1897, 2585, 6006, 6757, 6758, 6924, 7338, 7526, 9481, 9700, 10200, 10507], "Neopica": [7974, 10604], "Engine Software": [2228, 3422, 8191, 9043], "Panic Button": [5618, 6510, 8967, 9298], "Atari, Atari SA": [6521, 9656, 9719, 9910, 9934], "Cyanide, Cyanide Studios": [4691, 4907, 7832], "Tigon": [8790], "Oxygen Interactive": [4909], "Panther Software": [9502], "FreeStyleGames": [1418, 1707, 1784, 1858, 2008, 2406, 2680, 4102, 4496], "Koei Tecmo Games": [5759, 5804, 6902, 6942, 7612, 7664, 8094, 8938, 9487], "Croteam": [6167, 7901, 8359, 9525, 10379], "Saffire": [3208, 5701, 6287], "Ganbarion": [4165, 4447, 5572, 8241], "Rocksteady Studios, Iron Galaxy Studios": [6573], "Big Fish Games": [9356, 9551], "Polygon Magic": [4058, 7804, 8037], "Escape": [5635], "Eagle Dynamics": [9423], "Shin'en": [10619], "Taito Corporation": [3894, 5152, 7188, 7946, 8092, 8631, 9446, 9790, 10582, 10644], "VIS Entertainment": [734, 3142, 4709, 5901, 8146], "Victor Interactive Software": [3540, 4040], "Gearbox Software": [281, 331, 540, 582, 1639, 1642, 1735, 1753, 1776, 1952, 2275, 2449, 2464, 3103, 3112, 3278, 4149, 4650, 5711, 5714, 6217, 6604, 6688, 7721, 8163, 9158, 9273, 9675, 9801, 10408, 10442], "Genuine Games": [724, 3220, 5619, 7124], "Tactical Development": [6926], "Ubisoft Reflections": [1592, 2162, 5639, 5954], "Just For Fun": [8606], "Irrational Games": [649, 780, 2267, 9662], "Crystal Dynamics": [1034, 1404, 1449, 1739, 1795, 2674, 2768, 2839, 2941, 3147, 3547, 3591, 3722, 5267, 5483, 5592, 5741, 6271, 6545, 6602, 7007, 7829, 8518, 8554], "Sony Interactive Entertainment": [4713, 10334], "Reality Pump": [2138, 2750, 3092, 5375], "Quantic Dream": [334, 831, 6175, 7295, 9895], "Phoenix Games Studio": [3357, 6642], "Computer Artworks": [3207, 5421], "Electronic Arts, Rebellion": [1496], "Bullfrog Productions": [489, 591, 3019, 5199, 8537], "EA DICE, Danger Close": [383], "Slam Games": [6612], "Kung Fu Factory": [6769, 7754], "Studio 33": [6364, 6553], "Ignition Entertainment": [4410, 5850, 5984], "Virtual Toys": [3393, 6650, 9224], "Opera House": [8972, 9852], "High Impact Games": [2576, 3119, 4103], "Introversion, Double Eleven": [9375, 10623], "Longtail Studios": [1485, 7462, 8354, 9853], "8ing/Raizing": [1455, 1494, 2879], "Gearbox Software, 3D Realms": [1837, 1993, 3468], "2K Shanghai": [4643], "Bigben Interactive, Red Wagon Games": [10536], "eGames": [6195], "The Code Monkeys": [911], "Hyper-Devbox": [8843], "Digital Eclipse": [218, 2891, 3512, 4727, 5721, 5989, 6232, 7732, 7805], "Team Bondi": [314, 409], "Moss": [6852, 10424], "Clockwork Games": [7260, 10269], "Game Arts": [21, 2669, 2964, 3651, 3831, 3867, 4256, 4772, 5162, 5395, 7034, 9354], "Stainless Steel Studios": [8791], "Pixel Tales": [5525], "Good-Feel": [1114], "Namco Bandai Games America": [6013, 6951, 7685, 9846], "Cranky Pants Games": [5275, 7843, 8788, 9281], "Midway Studios - Austin": [2582, 3148, 4287, 4973, 7687], "RED Entertainment": [4327, 8596], "Blitz Games": [986, 1217, 1289, 2908, 2950, 2974, 3011, 3151, 3153, 3608, 3642, 3985, 4063, 4449, 4611, 5011, 5170, 5188, 5200, 5216, 5321, 5685, 5946, 6238, 6539, 6901, 7013, 7051, 7392, 7551, 7560, 7839, 8063, 8880, 10398], "Exakt": [535, 646, 1328, 2624, 3542, 4450, 5802, 6668], "Exient Entertainment": [1017, 1989, 2307, 3114, 4332, 4442, 4591, 5155, 6048, 7343], "Infogrames": [6774, 10278], "Kronos Digital Entertainment": [5654], "Deck 13": [6585, 6773, 8647], "Frontier Developments, Various": [9634], "BioWare": [325, 333, 361, 446, 553, 624, 801, 976, 994, 1341, 1555, 1627, 1852, 2052, 2149, 2346, 2487, 2803, 2881, 3297, 3500, 3562, 4480, 5809, 6392, 9413, 9680], "SCEE": [1781, 3271, 3673, 5564, 5735, 6749, 7181], "The Coalition": [1062], "Zushi Games Ltd": [7559], "Stormfront Studios": [160, 2035, 2110, 2598, 2799, 5411, 5490, 6428, 7028, 7611, 7776], "Naps Team": [9097], "Psyonix": [3723, 4892, 8268, 8515], "Sandlot": [3809, 6264, 7828, 8125, 8326], "Mentor Interactive": [9398], "Check Six Games": [631], "Shift, Bandai Namco Games": [7704], "2K Marin": [552, 894, 4754, 4844, 5185, 8660], "Neko Entertainment": [3752, 6145, 6419, 8177, 8260, 8334, 9771, 10053, 10164], "Classic Media Distribution Limited": [5556], "Triumph Studios": [3493, 4044, 4114, 9370, 9896], "Epic Games": [78, 96, 98, 874, 2233, 2554, 3047, 4387, 8351, 9922, 10191, 10235], "Tilted Mill": [9168, 9787], "Tiwak": [9368], "Asylum Entertainment": [10159], "Big Red Button Entertainment": [4140], "Gaslamp Games": [8983], "Camelot Software Planning": [906, 1206, 8159], "Vicious Cycle": [2424, 4336, 5206, 5404, 5593, 5961, 6627, 6713, 6958, 7070, 7139, 7401, 8196, 8799, 10246, 10501], "Dice, Danger Close": [431, 2978], "EA Canada, Nihilistic": [1958, 3637, 4377], "Silicon Dreams": [7472, 7707], "Headfirst Productions": [8336], "Nitro+": [8291], "BioWare, Demiurge Studios": [2215], "Eidos Interactive": [4019, 4616, 7084, 9677, 10489], "8Monkey Labs": [7377], "Impulse Games": [3884, 5823, 9243], "Sega": [533, 868, 1152, 1375, 1460, 2114, 3082, 3210, 3320, 3738, 3835, 4001, 4375, 4743, 4842, 4890, 4956, 5575, 5697, 6259, 6411, 7083, 8266, 8734, 9037], "Buzz Monkey": [1616], "Electronic Arts": [49, 132, 432, 638, 666, 689, 771, 925, 1054, 1224, 1226, 1319, 1363, 1374, 1475, 1668, 1706, 1726, 1794, 1905, 2068, 2078, 2080, 2154, 2172, 2190, 2262, 2296, 2334, 2409, 2501, 2552, 2571, 2634, 2716, 2729, 2753, 2756, 2757, 2894, 3048, 3096, 3185, 3307, 3343, 3350, 3370, 3490, 3521, 3532, 3592, 3874, 3908, 4169, 4265, 4426, 4553, 4817, 4939, 5118, 5250, 5388, 5597, 6014, 6263, 6266, 6860, 6922, 6998, 7156, 7381, 7498, 7572, 7582, 7639, 7799, 7916, 8023, 8214, 8594, 8781, 9618, 10527], "Circus Freak": [4339, 6535], "Freedom Factory Studios": [7414, 9594, 10513], "Sega, Sonic Team": [1036, 3451], "Reflections Interactive": [95, 155, 885, 1195, 1976, 4401, 8165, 9585], "Urban Games": [9209], "Ubisoft Romania": [2546, 2642, 3596, 4699, 6237, 6440, 6606, 7703, 8861, 8927, 9990], "GameCo": [10129], "Hypnos": [6207], "Namco Bandai Games, Monkey Bar Games": [7771, 7819, 8609], "Eighting/Raizing": [3825, 5668, 8982], "MumboJumbo": [5862, 9090, 9357], "G1M2": [7622], "Ubisoft Shanghai": [421, 956, 1179, 1670, 1882, 1937, 2269, 3479, 3936, 4662, 4693, 4955, 6248, 6625, 6994, 7183, 7648, 8018, 8081, 8442, 8513, 9312, 9836], "G.Rev": [8944], "K2, Kurogane": [6473], "CiRCLE": [9192, 10165], "ZigZagIsland": [9655], "Team 17": [5105, 5960, 6707, 7006, 7289, 7846, 8193, 8210, 8383, 8407, 8746, 8794, 9058, 9165, 9426, 9730, 10123, 10195, 10232, 10403, 10633], "Realmforge Studios": [7404], "1C, Ino-Co, 1C Company": [9361, 10242], "GSC Game World": [8384, 8465, 9227, 9572], "Tantatus": [6889], "Gameinvest": [8661], "Rainbow Studios": [484, 557, 656, 1216, 1465, 1634, 1647, 1701, 2104, 2147, 2192, 2936, 3089, 3128, 3240, 3434, 3520, 3659, 4000, 4180, 4733, 4779, 5133, 5336, 5386, 6283, 6906, 8458, 9041, 9610], "Delphine Software International": [2249], "Bugbear": [3643, 5926, 5943, 6054, 6997, 7132, 8923, 10013, 10488], "Y's K": [4776], "Vicious Cycle, Little Orbit": [10031, 10032], "Nihilistic": [3911, 5453, 5832], "Melbourne House": [1127, 2943], "ApolloSoft": [10002], "FASA Studio": [1754, 3068], "EA Bright Light": [992, 1999, 2305, 2492, 2578, 2612, 3182, 3563, 3704, 3946, 3983, 3995, 4052, 4120, 4428, 4472, 4802, 6038, 6458, 7256, 8388, 9483], "Metro3D": [7552], "Kush Games, Visual Concepts": [1946, 2548, 9576], "FireFly Studios": [5967, 6995, 7136, 9780, 10218], "Activision, Traveller's Tales": [7571], "Axis Entertainment": [6659], "Titus Software": [1644, 6185, 10117], "Nintendo, Nd Cube": [869, 3397], "Seven45 Studios": [6382, 6822], "Revolution Software": [4924, 8218, 8503, 10075, 10127, 10188], "NuFX": [391, 1470, 2250], "Epic Games, People Can Fly": [1487, 2807, 6064], "Pitbull Syndicate": [1067, 3355], "Deibus Studios": [1914, 7161, 7548, 9985], "Treyarch": [15, 16, 17, 22, 62, 118, 172, 285, 410, 416, 835, 908, 930, 952, 1015, 1041, 1250, 1305, 1333, 1338, 1397, 1814, 2079, 2213, 2301, 2347, 2610, 3435, 3470, 3549, 3691, 3879, 3960, 3978, 5278, 5657, 6893, 7231, 7253, 7379, 8403, 9498, 10124], "Andamiro U.S.A. Corp.": [8484, 9997], "Psikyo": [6710], "Hudson Soft": [818, 4122, 5904, 6888, 7168, 7241, 7895, 8805, 9578], "CAProduction": [453, 1901, 4053, 8860], "Media Vision, Contrail": [2383], "The Tangentlemen": [9754], "Ion Storm": [3951, 5248, 5847, 10453], "Blueshift": [4943], "Tantalus Interactive, Tantatus, Nintendo": [1471], "Spike, Namco Bandai Games": [343, 1478], "Deep Silver, Sproing Interactive Media, Sproing": [5236], "Shade": [4197], "Wizarbox": [7662, 9670, 9823, 10458], "Nautilus": [4896, 6284], "Amaze Entertainment": [2989, 4390, 4785, 5664], "Performance Designed Products": [5709], "Zoo Digital Publishing": [10022], "Nintendo, Intelligent Systems": [3384], "Nadeo": [3872, 8278, 10515], "Crea-Tech": [9637], "Syscom": [6646], "Red Storm Entertainment, Ubisoft Montreal": [3412, 3851, 8829], "Elixir Studios": [10303], "Beenox": [565, 2545, 3262, 3351, 3788, 3823, 4200, 4696, 4766, 4894, 5073, 5120, 5557, 5861, 5880, 7250, 7608, 9533, 9831, 9943, 10434], "Bongfish": [5273, 9130], "Ubisoft Montpellier": [611, 698, 1003, 1330, 1500, 1503, 2265, 2563, 2784, 3312, 3907, 4018, 4601, 4665, 4845, 4884, 5247], "Zono Inc.": [5487, 7692], "Ubisoft Paris": [65, 898, 958, 1590, 2229, 2398, 2619, 3697, 5640, 5829, 7395, 7621, 8223, 8858, 9215, 9216, 9321, 9431], "Blast! Entertainment Ltd": [8639, 9971], "MileStone Inc.": [7902], "Liquid Dragon Studios": [8761], "Idol FX": [8088], "Runtime": [8224], "Hypnotix": [3815, 4632, 5285, 7759, 7858, 8959, 9113], "Terminal Reality": [751, 1817, 2360, 2378, 2869, 3374, 4095, 4506, 4887, 5016, 5187, 5315, 5834, 6203, 6377, 6446, 6939, 6968, 7830, 8557, 9032, 9391, 9712, 10377, 10415], "Naughty Dog, SCE/WWS": [147], "SEK Ost": [9742], "Arika": [1429, 1785, 1809, 5909, 9314, 10292], "HAL Labs": [72, 817, 842, 2210, 2843], "Fresh 3D": [8587], "Ubisoft Montreal": [111, 112, 127, 152, 193, 199, 213, 216, 275, 294, 336, 340, 381, 479, 525, 545, 634, 750, 828, 829, 859, 875, 1027, 1069, 1074, 1098, 1121, 1170, 1176, 1321, 1322, 1347, 1399, 1501, 1562, 1580, 1693, 1748, 1763, 1879, 1900, 2030, 2180, 2199, 2281, 2352, 2403, 2510, 2522, 2531, 2577, 2662, 2700, 2812, 2912, 2991, 3192, 3789, 3794, 3817, 3973, 4308, 4338, 4633, 4814, 4995, 5296, 5573, 5642, 5724, 5746, 5916, 5947, 6072, 6955, 7126, 7173, 7845, 7864, 7927, 8348, 8462, 8605, 8755, 8896, 9094, 9350, 9427, 9793, 10205, 10476], "Guerrilla": [339, 399, 413, 1601, 5109], "Cave": [4380, 8651, 8665], "CCP": [5307, 7323], "Vanillaware": [2473, 2772, 5353, 8272], "Sumo Digital, Playground Games": [1933], "Targem Games": [9542], "TOSE": [2048, 2443, 2819, 3078, 4349, 6630], "Paradox Development Studio": [8003, 8546, 9019, 9774, 10320], "Monte Cristo Multimedia": [8209, 8939, 9782], "People Can Fly": [9232, 9967], "Eighting, Takara Tomy": [5745], "Mid Carolina Media": [7874], "Neon Studios, Kaiko": [9673, 10487], "Virtuos": [1157, 2783, 3377, 3892, 4796, 6825, 7032, 7491, 7741, 8028, 8287], "Red Storm Entertainment, Ubisoft Paris": [1468, 1481], "Supersonic Software": [7037, 10109, 10263, 10589], "Tose Software": [10044], "Etranges Libellules": [2629, 2871, 3247, 3368, 3505, 4143, 5757, 6445], "Kando Games": [9238], "id Software": [850, 1104, 2608, 3036, 3717, 7194, 9485], "Nintendo EAD Tokyo": [60, 1242], "Tommo": [8289], "Dimps Corporation, Dream Execution": [8460], "Bits Studios": [5041, 6526, 6894, 7059, 8461, 8723], "Dusenberry Martin Racing": [8753, 9153], "Blue Byte": [4142, 4725, 6491, 6634, 7114, 9733], "Cryptic Studios": [9788], "1C: Maddox Games": [8584, 8950], "Coresoft": [1579, 2886, 4443, 5193, 7456, 8179, 10197], "Clover Studio": [2369, 2393, 4378, 5098, 5197, 8156, 8476], "Magellan Interactive": [5790], "Zed Two Limited": [7102, 8164, 9751], "Playstos Entertainment": [9968, 10107], "Carbine Studios": [6075], "Treyarch, Sledgehammer Games": [1853], "Project Soul": [2009, 2528], "Sinister Games": [4214], "Brain Toys": [9644], "Namco Bandai Games America, Namco Bandai Games": [1118, 4921, 5413, 5734, 5971], "Revistronic": [7897], "Dreamworks Games": [2496], "Sanrio Digital": [5023], "ZeniMax Media": [1134, 1698], "Two Tribes": [6289], "Nival Interactive": [9027], "Gust, Idea Factory": [5727], "Valcon Games": [7661], "Scholastic, Inc.": [2994], "Yager": [2714, 3382, 5033, 8870], "Ubisoft Milan": [2173], "Firaxis Games": [793, 1851, 1945, 2113, 2379, 2583, 3750, 4800, 4963, 5948, 6360, 8845], "Valve Software": [204, 219, 495, 594, 707, 774, 1342, 1992, 2429, 3753, 6378, 7660, 9868], "Psygnosis": [3337, 3882, 4707], "Edge of Reality": [398, 2010, 2751, 2962, 3330, 3654, 3869, 4175, 4245, 4583, 4595, 5089, 5325, 5398, 7296, 7905, 8111], "Capcom, Pipeworks Software, Inc.": [1868, 3291], "Nordic Games Publishing": [6252, 8313, 8709, 9365, 9573, 9980, 10051, 10367], "Art": [642], "Core Design Ltd.": [128, 161, 516, 1178, 2405, 3404, 3897, 5148, 7496], "1C, 1C Company": [9806, 10392], "System Prisma": [9185], "Grasshopper Manufacture": [2268, 2670, 3013, 3553, 4530, 5044, 5613, 6169, 6759, 7640, 7739, 8590], "VSTEP": [8818, 10322], "Konami Computer Entertainment Hawaii": [1306, 2723, 3366, 8009, 10114], "Spicy Horse": [2547, 2945, 6848], "Attention To Detail": [4488, 6482, 6667, 7604, 9450, 9503], "Digital Extremes, 2K Marin": [993], "SuperBot Entertainment": [1584], "Epicenter Studios": [2327, 8760, 8847], "Black Hole Games": [6954, 9580], "Mercury Steam": [1352, 2256, 5439, 7501, 9155, 9797], "Blue Tongue Entertainment": [1572, 3270, 3776, 4310, 4550, 5262, 5715, 6160, 6882, 7066, 7389, 8160, 9024, 9724], "Enterbrain": [8130], "Pronto Games": [7249], "Nintendo": [0, 1, 2, 3, 4, 5, 7, 27, 69, 71, 93, 130, 145, 162, 164, 176, 177, 186, 223, 235, 258, 305, 310, 316, 536, 832, 860, 1076, 1236, 1349, 1656, 1808, 1876, 2448, 3678, 5942], "BattleBorne": [8389, 9448], "Wow Entertainment": [3564, 5586, 5780, 6472, 6865, 6976, 7673], "10tacle Studios": [6037], "Luxoflux, Inc.": [303, 332, 684, 1029, 1479, 2699, 2857, 3123], "SCi": [1772, 10485], "eV Interactive": [6680], "Naughty Dog": [70, 79, 82, 104, 119, 154, 250, 392, 692, 2707], "Ghost Games": [630, 1158, 1917, 2178, 4746], "EA Phenomic": [10421], "Tango Gameworks": [718, 1825, 2220, 3104, 4479], "Red Wagon Games": [8540], "Broadsword Interactive": [6112, 8579, 9387], "Cunning Developments": [2236, 7872], "Rebellion": [1426, 1457, 1576, 1829, 2198, 3125, 3858, 4216, 4420, 5322, 5447, 5457, 6503, 6698, 7092, 7116, 7117, 7331, 7566, 7627, 7731, 7968, 8909, 8924, 9106, 9661, 9918, 10145, 10206, 10258], "Majesco Games, Majesco": [382, 5666, 6666, 7040, 7290, 8451], "Super X Studios": [5264, 6722, 6805, 9234], "Tate Interactive": [10222, 10273], "2K Play": [9110], "Backbone Entertainment": [524, 1007, 2209, 2345, 4127, 4173, 5973, 7001, 7050], "Retro Studios": [87, 380, 719, 912, 1088, 2423], "New": [3049], "Engine Software, Re-Logic": [9458], "Phosphor Games Studio, LLC": [6610], "Trickstar Games": [6989, 7508, 9109], "Ludia": [5988], "Tabot": [7645], "Ubisoft, Ubisoft Montreal": [221, 273, 2697], "Koei, Omega Force": [2131, 2271, 3035, 4244, 4770, 5567, 6162], "High Voltage Software": [1203, 1667, 1830, 2244, 2611, 2673, 3143, 3299, 3342, 3653, 3658, 3692, 3913, 4014, 4125, 4196, 4559, 4899, 5401, 5794, 5842, 5852, 5938, 6053, 6156, 6387, 6467, 6504, 6648, 6762, 6777, 6887, 7008, 7011, 7085, 7203, 7212, 7257, 7351, 7690, 8248, 8481, 8549, 8642, 8712, 9841, 10030, 10620], "Trendy Entertainment": [9882], "Kemco": [5906, 7316, 7822, 9406, 10576], "Mastiff": [4493, 4681], "Metropolis Software": [7904], "Volatile Games": [4406, 5287], "Deep Silver Dambuster Studios": [3828, 6405, 9211], "Insomniac Games": [184, 243, 467, 950, 1181, 1314, 7851, 8361, 9363, 10435], "FeelPlus": [5456, 5768, 7198, 7391], "Pacific Coast Power & Light": [2124, 2667, 3499, 3826, 6572, 7878], "Flying Tiger Development": [8820], "ACOT": [6652], "Piranha Bytes": [5067, 5086, 5566, 6365, 6421, 7596, 7742, 8221, 8529], "Krome Studios": [688, 819, 1169, 1258, 1909, 2787, 3325, 3589, 4503, 4940, 5232, 5355, 5548, 5589, 5634, 5873, 6498, 7063, 7077, 7592, 7781, 7960, 7976, 8299, 8430, 8597, 8932, 9422, 9726], "Secret Level": [2203, 2592, 3268, 3396, 4006, 4023, 4771, 7601, 10171], "Tecmo Koei Canada": [5599], "SquareSoft": [37, 51, 55, 90, 121, 123, 469, 577, 691, 960, 1302, 1777, 1898, 1969, 2569], "Starsphere Interactive": [7320, 9012], "Eden": [2188, 2388, 5450], "Gust": [3326, 4649, 4922, 5436, 5656, 6068, 6114, 6763, 7368, 8292, 8295, 8450], "Screenlife Games, WXP": [3001], "iRock Interactive": [7632], "Ritual Entertainment, Avalanche Software": [3327, 5931], "Santa Cruz Games": [7247], "K2 LLC": [1300, 3910, 5192, 5541, 7783, 9137], "Image Epoch, Imageepoch": [5513, 5921], "Acclaim Studios Austin": [1968, 2643, 3338, 4827], "Contraband Entertainment": [2914], "Kalypso": [2161, 8020, 8186, 8573, 9738, 10179, 10553], "Cyberlore Studios": [3647, 5417, 7383], "Cauldron Ltd.": [5412, 5779, 6278, 8424, 9384, 9555, 10178], "Piranha Games": [3020, 5211], "Enlight Software": [9261], "PuzzleKings": [9681], "Lightning Fish Games": [3662, 7720, 7815, 9703, 10158], "Io Interactive": [351, 567, 759, 1248, 1896, 2840, 2910, 3599, 3739, 3887, 3895, 4266, 5001, 5261, 5822, 6337, 6596, 6682, 9271, 10019], "Headgate": [10467], "EA Canada": [74, 85, 181, 195, 196, 225, 245, 276, 286, 317, 320, 338, 434, 436, 512, 518, 520, 644, 743, 756, 796, 813, 820, 882, 917, 1014, 1066, 1077, 1131, 1139, 1159, 1173, 1202, 1204, 1284, 1345, 1420, 1461, 1476, 1554, 1666, 1680, 1710, 1730, 1930, 1940, 2021, 2085, 2129, 2136, 2204, 2257, 2317, 2348, 2350, 2414, 2568, 2595, 2603, 2631, 2646, 2738, 2763, 2769, 2823, 2831, 2845, 2853, 2899, 2934, 2946, 3026, 3067, 3177, 3180, 3193, 3324, 3443, 3480, 3513, 3560, 3565, 3568, 3575, 3611, 3634, 3645, 3729, 3744, 3838, 3914, 3938, 3943, 4002, 4016, 4029, 4059, 4090, 4126, 4229, 4269, 4275, 4413, 4452, 4626, 4704, 4719, 4724, 4904, 5078, 5123, 5171, 5272, 5305, 5529, 5870, 5887, 5934, 5970, 6007, 6138, 6176, 6187, 6321, 6327, 6460, 6594, 6927, 7202, 7454, 7696, 7734, 7757, 7961, 8077, 8572, 8612, 8773, 9166, 9902, 10078, 10280], "Rocksteady Studios, Virtuos": [4580, 7054], "WB Games Montreal": [515, 668], "Seta Corporation": [5538, 6376], "Tornado Studios": [4716], "Punchline, Shirogumi": [9819], "Purple Hills": [10119], "Phoenix Entertainment": [5119], "Farsight Studios": [786, 2533, 3051, 5116, 5672, 5830, 6497, 6816, 6938, 7227], "FuRyu": [7943], "Vivarium": [2809, 7012], "Venom Games": [4077, 4491, 4759, 7319], "Armature Studio, comcept": [6277], "Sony Online Entertainment": [3303, 5423, 5610, 8350], "Gogii Games": [9970], "Destineer": [2760, 4635, 5463, 5628, 6235, 6397, 7100, 7469, 7888, 9246, 9484, 9800, 10295], "SCS Software": [2949, 6544], "Indie Built": [1863, 4354, 4700], "Sports Interactive": [927, 1162, 1287, 1291, 1336, 2321, 3093, 7464, 8100, 10037, 10294, 10376], "Blue Planet Software": [590], "Disney Interactive": [4193, 7688], "War Drum Studios": [3298, 7088], "Blue Castle Games": [942, 1045, 2887, 3724, 4320, 4548, 5198, 5383, 6004, 6452, 6560, 7848, 8058, 9590, 10274], "Red Tribe": [3623, 4976, 6810, 6988, 7792, 8415], "Pinegrow": [7919], "Xpec": [1663, 2278, 4321, 5488, 7106, 7588, 7700], "Infinity Ward, Sledgehammer Games": [13, 19, 766], "Atomic Games": [10643], "Light Weight": [1277, 3590, 6599, 8226], "T&E Soft": [2837, 5902], "Daedalic Entertainment": [6223, 7235, 8139, 9252], "Dimps Corporation": [326, 482, 645, 1351, 2130, 3012, 3748, 4038, 4880, 5034, 5351, 5671, 6972, 7740, 8091, 8961], "Starbreeze": [2243, 3144, 3256, 4292, 4792, 5665, 6305, 6413, 6449, 8964, 10482], "DMA Design, Rockstar North": [10369], "Frontier Developments": [502, 841, 2253, 3257, 3331, 3371, 4502, 5992], "Artificial Studios, Immersion Software & Graphics": [6929], "Snap Dragon Games": [9005], "Hijinx Studios": [4066, 4323, 6307], "Raster": [2808], "Idea Factory": [7144, 9176], "Black Ship Games": [7441, 8993, 10008], "Capcom": [106, 138, 140, 201, 253, 274, 324, 347, 357, 407, 505, 527, 542, 583, 588, 632, 636, 752, 785, 870, 971, 974, 1068, 1072, 1078, 1222, 1315, 1474, 1598, 1687, 1848, 1923, 1967, 2001, 2020, 2034, 2116, 2260, 2324, 2325, 2338, 2616, 2622, 2690, 2933, 3041, 3373, 3389, 3600, 3890, 4208, 4234, 4306, 4343, 4517, 4655, 4762, 4813, 4833, 4891, 5079, 5115, 5215, 5295, 5468, 5475, 5545, 6172, 6368, 6417, 6430, 6589, 6684, 6701, 6830, 6982, 7209, 7258, 7371, 7390, 7614, 7712, 7836, 7889, 8043, 8062, 8145, 8171, 8393, 8444, 8452, 8533, 8878, 9020, 9021, 9074, 9089, 9496, 9568, 9577, 9584, 9607, 9646, 9709, 9731, 9884, 10183, 10339], "CokeM Interactive": [5923, 8357], "Ninja Theory": [821, 1913, 2677, 2727, 3246], "Red Zone Entertainment": [3627], "Heavy Iron Studios": [496, 731, 806, 1492, 1582, 1604, 1818, 2410, 2607, 2715, 2872, 3511, 3764, 4274, 4473, 4561, 4575, 4730, 4798, 6000, 7624, 7981, 10217, 10241], "Pandemic Studios": [256, 260, 738, 798, 1432, 1774, 1780, 2025, 2071, 2351, 2896, 3016, 4239, 4694, 5871, 6991, 8147, 8212, 8511, 8831, 9693], "ArtePiazza": [7313], "Atlus": [2145, 3688, 3901, 4129, 4315, 5805, 6923], "Funcom": [5806, 6315, 9107, 9592, 10203], "Snowblind Studios": [1135, 1183, 1815, 1870, 2295, 5425, 5607], "Treasure": [3245, 7423, 7576, 8108, 8718, 8768], "Namco Bandai Games, Bandai Namco Games": [2623], "DMA Design": [20, 283], "Unknown": [14, 25, 35, 43, 50, 53, 54, 57, 59, 61, 73, 76, 83, 110, 116, 124, 126, 135, 142, 143, 149, 150, 157, 158, 167, 173, 187, 200, 202, 205, 214, 217, 236, 240, 241, 247, 248, 251, 262, 263, 266, 268, 269, 271, 292, 293, 295, 297, 309, 311, 321, 337, 344, 354, 356, 369, 370, 374, 375, 378, 384, 385, 386, 387, 388, 390, 393, 401, 404, 408, 423, 439, 441, 442, 444, 451, 454, 455, 457, 461, 471, 475, 478, 481, 485, 488, 492, 493, 509, 510, 514, 522, 528, 544, 547, 559, 564, 572, 574, 578, 579, 584, 586, 596, 600, 601, 603, 607, 614, 615, 647, 660, 664, 670, 672, 673, 676, 677, 679, 682, 685, 687, 694, 697, 699, 700, 709, 715, 720, 722, 725, 728, 729, 737, 739, 742, 747, 748, 753, 754, 758, 760, 762, 768, 772, 781, 782, 783, 784, 788, 789, 792, 800, 822, 825, 827, 840, 844, 849, 851, 852, 861, 863, 867, 888, 891, 899, 901, 904, 907, 910, 913, 914, 915, 916, 922, 923, 924, 926, 932, 935, 937, 943, 944, 947, 949, 957, 962, 965, 966, 968, 975, 977, 979, 981, 990, 996, 1002, 1005, 1009, 1010, 1018, 1020, 1025, 1030, 1033, 1035, 1040, 1044, 1053, 1055, 1061, 1063, 1064, 1079, 1084, 1086, 1087, 1089, 1095, 1097, 1099, 1100, 1101, 1102, 1108, 1117, 1120, 1123, 1124, 1132, 1136, 1137, 1155, 1161, 1163, 1164, 1165, 1172, 1180, 1196, 1197, 1199, 1207, 1208, 1209, 1210, 1211, 1213, 1221, 1223, 1229, 1235, 1237, 1240, 1246, 1247, 1251, 1256, 1262, 1263, 1267, 1269, 1273, 1281, 1282, 1285, 1290, 1297, 1298, 1307, 1308, 1311, 1313, 1316, 1320, 1326, 1329, 1343, 1348, 1353, 1354, 1355, 1358, 1370, 1377, 1381, 1388, 1390, 1392, 1393, 1396, 1400, 1402, 1403, 1405, 1412, 1413, 1417, 1421, 1424, 1425, 1439, 1451, 1454, 1458, 1459, 1483, 1493, 1497, 1506, 1508, 1509, 1510, 1512, 1513, 1515, 1518, 1522, 1533, 1537, 1541, 1566, 1567, 1568, 1583, 1585, 1586, 1589, 1593, 1595, 1602, 1603, 1605, 1607, 1609, 1612, 1617, 1619, 1621, 1630, 1651, 1652, 1653, 1659, 1660, 1662, 1664, 1665, 1669, 1674, 1675, 1682, 1697, 1699, 1704, 1718, 1719, 1725, 1727, 1728, 1729, 1731, 1733, 1736, 1742, 1743, 1745, 1746, 1761, 1764, 1767, 1783, 1788, 1790, 1793, 1797, 1801, 1823, 1831, 1834, 1838, 1843, 1844, 1849, 1850, 1861, 1869, 1875, 1877, 1880, 1885, 1887, 1892, 1895, 1903, 1906, 1912, 1919, 1925, 1926, 1938, 1941, 1944, 1948, 1950, 1954, 1955, 1961, 1964, 1966, 1973, 1974, 1975, 1977, 1978, 1979, 1982, 1983, 1984, 1985, 1990, 1991, 1995, 1996, 1997, 1998, 2011, 2013, 2014, 2018, 2023, 2024, 2031, 2036, 2038, 2039, 2041, 2055, 2056, 2057, 2060, 2061, 2063, 2070, 2081, 2082, 2083, 2090, 2094, 2098, 2106, 2107, 2120, 2122, 2125, 2126, 2127, 2128, 2132, 2133, 2141, 2148, 2151, 2152, 2156, 2164, 2165, 2167, 2170, 2171, 2175, 2176, 2181, 2185, 2189, 2191, 2195, 2200, 2201, 2206, 2214, 2216, 2217, 2218, 2219, 2223, 2224, 2227, 2230, 2231, 2232, 2234, 2235, 2246, 2248, 2251, 2254, 2258, 2261, 2264, 2274, 2276, 2279, 2280, 2289, 2291, 2294, 2297, 2298, 2299, 2302, 2304, 2318, 2319, 2320, 2322, 2331, 2332, 2333, 2340, 2349, 2353, 2355, 2357, 2363, 2367, 2375, 2382, 2384, 2392, 2394, 2399, 2402, 2407, 2408, 2411, 2412, 2417, 2428, 2430, 2438, 2439, 2441, 2445, 2465, 2466, 2470, 2471, 2472, 2474, 2475, 2477, 2481, 2485, 2486, 2490, 2491, 2494, 2495, 2499, 2506, 2508, 2509, 2512, 2516, 2517, 2521, 2529, 2535, 2537, 2539, 2540, 2542, 2549, 2550, 2551, 2556, 2558, 2559, 2562, 2566, 2570, 2573, 2581, 2591, 2594, 2602, 2609, 2618, 2639, 2644, 2647, 2650, 2671, 2676, 2679, 2681, 2682, 2685, 2686, 2687, 2691, 2692, 2695, 2696, 2701, 2702, 2704, 2706, 2709, 2713, 2718, 2719, 2728, 2732, 2733, 2734, 2735, 2740, 2742, 2743, 2746, 2762, 2765, 2773, 2775, 2780, 2791, 2793, 2795, 2804, 2805, 2806, 2813, 2832, 2835, 2838, 2844, 2849, 2850, 2851, 2852, 2854, 2856, 2860, 2864, 2866, 2873, 2874, 2877, 2883, 2893, 2895, 2903, 2907, 2917, 2919, 2921, 2922, 2929, 2938, 2939, 2951, 2966, 2968, 2970, 2972, 2975, 2976, 2977, 2979, 2984, 2985, 2990, 2993, 2995, 2996, 2998, 3000, 3004, 3008, 3009, 3014, 3015, 3018, 3021, 3022, 3031, 3032, 3034, 3039, 3046, 3057, 3058, 3059, 3060, 3061, 3066, 3069, 3073, 3079, 3081, 3094, 3095, 3107, 3108, 3109, 3110, 3115, 3120, 3121, 3124, 3134, 3135, 3139, 3141, 3146, 3149, 3155, 3158, 3159, 3161, 3163, 3164, 3165, 3166, 3169, 3172, 3173, 3174, 3183, 3186, 3187, 3188, 3191, 3197, 3202, 3204, 3206, 3216, 3217, 3221, 3223, 3224, 3228, 3229, 3230, 3231, 3234, 3235, 3236, 3238, 3241, 3242, 3243, 3248, 3258, 3259, 3261, 3266, 3269, 3272, 3274, 3275, 3279, 3284, 3300, 3301, 3304, 3319, 3332, 3333, 3335, 3336, 3339, 3346, 3352, 3353, 3356, 3358, 3359, 3360, 3361, 3362, 3363, 3375, 3378, 3381, 3387, 3390, 3392, 3398, 3401, 3406, 3407, 3411, 3415, 3417, 3426, 3429, 3430, 3431, 3433, 3436, 3437, 3440, 3441, 3442, 3447, 3450, 3452, 3457, 3463, 3472, 3481, 3487, 3488, 3491, 3496, 3498, 3503, 3506, 3507, 3508, 3509, 3514, 3524, 3525, 3527, 3531, 3536, 3538, 3539, 3541, 3543, 3546, 3552, 3555, 3556, 3561, 3566, 3569, 3571, 3574, 3576, 3577, 3578, 3579, 3581, 3583, 3585, 3588, 3601, 3605, 3609, 3610, 3615, 3617, 3619, 3620, 3624, 3625, 3631, 3639, 3641, 3649, 3657, 3660, 3665, 3668, 3671, 3674, 3680, 3683, 3685, 3686, 3707, 3714, 3715, 3716, 3732, 3735, 3737, 3741, 3743, 3758, 3765, 3766, 3768, 3770, 3773, 3774, 3775, 3782, 3785, 3787, 3790, 3792, 3793, 3796, 3799, 3801, 3803, 3804, 3807, 3808, 3812, 3814, 3816, 3820, 3821, 3833, 3834, 3837, 3839, 3841, 3847, 3852, 3863, 3864, 3873, 3876, 3883, 3893, 3898, 3906, 3909, 3912, 3915, 3916, 3918, 3920, 3926, 3927, 3929, 3935, 3937, 3940, 3941, 3944, 3945, 3955, 3963, 3967, 3968, 3971, 3972, 3975, 3984, 3986, 3987, 3989, 3993, 3994, 3997, 4007, 4008, 4013, 4017, 4025, 4030, 4031, 4035, 4037, 4042, 4046, 4054, 4055, 4064, 4069, 4070, 4071, 4072, 4078, 4083, 4084, 4086, 4087, 4092, 4098, 4110, 4112, 4115, 4121, 4123, 4131, 4132, 4133, 4138, 4139, 4141, 4144, 4145, 4150, 4152, 4154, 4155, 4156, 4157, 4158, 4159, 4160, 4161, 4166, 4167, 4172, 4174, 4177, 4178, 4182, 4185, 4186, 4190, 4192, 4195, 4199, 4201, 4204, 4211, 4217, 4222, 4223, 4226, 4233, 4236, 4240, 4242, 4243, 4251, 4252, 4253, 4264, 4271, 4272, 4273, 4278, 4279, 4280, 4283, 4285, 4294, 4295, 4296, 4297, 4298, 4299, 4300, 4301, 4302, 4303, 4311, 4314, 4318, 4319, 4326, 4330, 4335, 4337, 4341, 4342, 4346, 4347, 4348, 4355, 4358, 4361, 4364, 4372, 4376, 4379, 4382, 4391, 4397, 4399, 4408, 4416, 4422, 4430, 4433, 4436, 4437, 4444, 4445, 4448, 4455, 4457, 4463, 4465, 4466, 4468, 4469, 4475, 4476, 4477, 4486, 4498, 4499, 4512, 4513, 4514, 4515, 4516, 4518, 4529, 4535, 4537, 4538, 4539, 4541, 4543, 4544, 4549, 4555, 4556, 4560, 4565, 4569, 4571, 4573, 4578, 4579, 4581, 4585, 4586, 4587, 4592, 4600, 4602, 4604, 4606, 4609, 4613, 4621, 4622, 4623, 4624, 4625, 4630, 4636, 4638, 4645, 4648, 4654, 4657, 4659, 4663, 4666, 4668, 4671, 4672, 4679, 4682, 4687, 4695, 4697, 4698, 4701, 4710, 4723, 4731, 4734, 4735, 4736, 4737, 4738, 4739, 4740, 4741, 4742, 4749, 4750, 4753, 4758, 4760, 4761, 4763, 4765, 4767, 4768, 4774, 4777, 4782, 4783, 4786, 4787, 4789, 4793, 4801, 4806, 4811, 4818, 4820, 4824, 4825, 4826, 4829, 4831, 4834, 4836, 4837, 4847, 4850, 4856, 4862, 4863, 4864, 4865, 4866, 4867, 4868, 4870, 4873, 4878, 4879, 4881, 4888, 4889, 4895, 4900, 4911, 4915, 4916, 4930, 4932, 4933, 4934, 4935, 4941, 4945, 4950, 4952, 4953, 4961, 4966, 4968, 4972, 4974, 4975, 4977, 4980, 4984, 4989, 4991, 4992, 4997, 5005, 5008, 5012, 5013, 5020, 5021, 5022, 5024, 5025, 5031, 5036, 5039, 5042, 5043, 5047, 5048, 5049, 5051, 5052, 5054, 5056, 5060, 5062, 5066, 5070, 5074, 5076, 5080, 5085, 5091, 5092, 5093, 5094, 5095, 5097, 5100, 5104, 5107, 5110, 5111, 5126, 5130, 5136, 5139, 5140, 5141, 5142, 5144, 5145, 5153, 5156, 5159, 5167, 5169, 5176, 5177, 5178, 5179, 5181, 5182, 5189, 5195, 5196, 5202, 5204, 5207, 5209, 5210, 5214, 5217, 5220, 5221, 5222, 5225, 5226, 5227, 5228, 5229, 5230, 5233, 5237, 5240, 5242, 5243, 5246, 5255, 5260, 5263, 5274, 5279, 5281, 5282, 5288, 5289, 5297, 5301, 5302, 5303, 5311, 5314, 5316, 5317, 5318, 5323, 5326, 5330, 5331, 5332, 5337, 5339, 5345, 5346, 5349, 5357, 5359, 5364, 5365, 5366, 5367, 5368, 5369, 5370, 5371, 5372, 5373, 5374, 5379, 5380, 5382, 5385, 5387, 5389, 5391, 5396, 5407, 5410, 5416, 5419, 5422, 5427, 5438, 5442, 5444, 5448, 5449, 5455, 5469, 5470, 5472, 5473, 5480, 5492, 5494, 5495, 5497, 5501, 5503, 5504, 5506, 5509, 5515, 5516, 5517, 5518, 5519, 5520, 5521, 5522, 5526, 5530, 5533, 5539, 5549, 5551, 5552, 5553, 5554, 5558, 5559, 5561, 5562, 5565, 5576, 5579, 5596, 5606, 5611, 5614, 5622, 5627, 5632, 5643, 5645, 5646, 5648, 5653, 5655, 5659, 5660, 5661, 5673, 5674, 5675, 5682, 5683, 5684, 5688, 5690, 5691, 5694, 5696, 5698, 5699, 5710, 5723, 5725, 5728, 5733, 5748, 5749, 5756, 5760, 5762, 5777, 5778, 5786, 5788, 5793, 5795, 5796, 5810, 5816, 5817, 5826, 5827, 5831, 5833, 5835, 5836, 5840, 5845, 5846, 5848, 5851, 5855, 5856, 5857, 5863, 5864, 5865, 5868, 5869, 5874, 5877, 5884, 5885, 5891, 5892, 5893, 5895, 5898, 5900, 5903, 5907, 5910, 5913, 5917, 5920, 5927, 5941, 5949, 5951, 5953, 5962, 5963, 5969, 5972, 5976, 5978, 5979, 5991, 5993, 6008, 6010, 6015, 6017, 6022, 6023, 6024, 6025, 6026, 6027, 6028, 6029, 6030, 6031, 6032, 6033, 6034, 6035, 6039, 6041, 6046, 6047, 6049, 6057, 6058, 6060, 6061, 6066, 6067, 6069, 6070, 6071, 6073, 6079, 6080, 6087, 6089, 6090, 6097, 6100, 6101, 6102, 6103, 6109, 6110, 6115, 6125, 6128, 6131, 6136, 6137, 6147, 6150, 6159, 6168, 6173, 6182, 6186, 6188, 6190, 6191, 6192, 6193, 6196, 6197, 6205, 6208, 6209, 6210, 6212, 6213, 6215, 6216, 6221, 6222, 6225, 6228, 6239, 6242, 6245, 6249, 6250, 6253, 6255, 6256, 6258, 6260, 6267, 6269, 6273, 6275, 6293, 6297, 6303, 6304, 6308, 6317, 6318, 6319, 6320, 6322, 6325, 6331, 6333, 6334, 6335, 6338, 6340, 6348, 6350, 6358, 6361, 6363, 6367, 6369, 6381, 6383, 6384, 6385, 6386, 6388, 6389, 6391, 6394, 6396, 6399, 6401, 6409, 6410, 6412, 6414, 6415, 6422, 6427, 6431, 6432, 6434, 6435, 6436, 6438, 6441, 6443, 6444, 6447, 6450, 6451, 6453, 6456, 6459, 6462, 6463, 6469, 6474, 6476, 6477, 6478, 6483, 6488, 6490, 6492, 6493, 6495, 6496, 6499, 6501, 6505, 6508, 6509, 6512, 6514, 6515, 6516, 6519, 6522, 6529, 6531, 6537, 6546, 6548, 6555, 6565, 6566, 6568, 6569, 6579, 6580, 6581, 6582, 6587, 6603, 6607, 6608, 6613, 6618, 6622, 6629, 6636, 6643, 6644, 6647, 6649, 6653, 6654, 6655, 6656, 6657, 6660, 6662, 6663, 6665, 6670, 6671, 6672, 6675, 6686, 6692, 6693, 6694, 6695, 6699, 6700, 6702, 6708, 6712, 6715, 6716, 6718, 6723, 6724, 6726, 6727, 6729, 6730, 6733, 6734, 6740, 6742, 6743, 6754, 6756, 6768, 6770, 6772, 6781, 6784, 6791, 6792, 6793, 6794, 6795, 6798, 6802, 6807, 6811, 6815, 6817, 6821, 6832, 6834, 6836, 6838, 6840, 6846, 6850, 6854, 6862, 6863, 6864, 6874, 6876, 6877, 6879, 6880, 6883, 6884, 6890, 6900, 6903, 6904, 6908, 6917, 6918, 6920, 6921, 6931, 6935, 6940, 6944, 6947, 6953, 6961, 6962, 6966, 6967, 6970, 6974, 6975, 6981, 6985, 6992, 6996, 7003, 7010, 7018, 7019, 7020, 7021, 7022, 7023, 7024, 7025, 7026, 7035, 7036, 7043, 7047, 7048, 7052, 7056, 7057, 7058, 7072, 7076, 7078, 7079, 7081, 7082, 7086, 7089, 7093, 7096, 7097, 7099, 7105, 7107, 7110, 7112, 7118, 7119, 7123, 7127, 7128, 7129, 7135, 7143, 7145, 7146, 7150, 7153, 7159, 7170, 7172, 7176, 7178, 7179, 7180, 7187, 7190, 7192, 7199, 7201, 7205, 7208, 7210, 7211, 7213, 7214, 7215, 7223, 7236, 7237, 7238, 7245, 7248, 7254, 7259, 7261, 7263, 7265, 7266, 7267, 7268, 7269, 7270, 7271, 7272, 7273, 7274, 7275, 7276, 7277, 7278, 7280, 7284, 7287, 7288, 7292, 7300, 7301, 7304, 7305, 7307, 7308, 7311, 7312, 7315, 7318, 7321, 7324, 7326, 7328, 7335, 7336, 7340, 7342, 7345, 7346, 7347, 7352, 7354, 7357, 7358, 7361, 7363, 7365, 7366, 7370, 7372, 7375, 7380, 7384, 7386, 7387, 7388, 7393, 7398, 7400, 7402, 7408, 7409, 7410, 7411, 7419, 7424, 7430, 7433, 7445, 7450, 7451, 7452, 7458, 7459, 7460, 7461, 7463, 7465, 7468, 7475, 7477, 7478, 7480, 7481, 7485, 7488, 7489, 7493, 7495, 7505, 7506, 7507, 7510, 7511, 7512, 7514, 7515, 7516, 7517, 7518, 7519, 7520, 7523, 7525, 7527, 7532, 7535, 7538, 7541, 7543, 7544, 7547, 7549, 7550, 7553, 7555, 7558, 7562, 7570, 7575, 7579, 7584, 7585, 7586, 7591, 7593, 7597, 7598, 7600, 7606, 7607, 7609, 7613, 7615, 7616, 7620, 7625, 7628, 7630, 7631, 7633, 7634, 7638, 7644, 7647, 7650, 7652, 7655, 7656, 7657, 7658, 7666, 7669, 7671, 7674, 7675, 7678, 7679, 7689, 7691, 7695, 7697, 7698, 7701, 7711, 7713, 7717, 7718, 7723, 7724, 7725, 7727, 7730, 7735, 7737, 7744, 7750, 7760, 7768, 7769, 7770, 7772, 7774, 7779, 7780, 7784, 7785, 7786, 7787, 7788, 7789, 7790, 7796, 7798, 7800, 7801, 7803, 7806, 7810, 7811, 7820, 7821, 7825, 7831, 7833, 7834, 7842, 7852, 7853, 7855, 7856, 7857, 7859, 7860, 7861, 7865, 7868, 7870, 7876, 7880, 7881, 7882, 7884, 7885, 7887, 7903, 7906, 7909, 7910, 7914, 7918, 7922, 7923, 7925, 7926, 7928, 7930, 7932, 7939, 7940, 7944, 7945, 7947, 7948, 7949, 7950, 7957, 7958, 7959, 7962, 7963, 7970, 7972, 7980, 7983, 7988, 7993, 7994, 7996, 7998, 7999, 8000, 8001, 8007, 8011, 8013, 8016, 8019, 8021, 8022, 8027, 8029, 8030, 8034, 8042, 8046, 8049, 8050, 8053, 8056, 8060, 8067, 8068, 8069, 8070, 8071, 8072, 8073, 8076, 8078, 8085, 8086, 8093, 8095, 8099, 8105, 8106, 8107, 8109, 8112, 8114, 8117, 8121, 8122, 8126, 8127, 8129, 8132, 8137, 8140, 8141, 8144, 8148, 8149, 8150, 8153, 8154, 8157, 8167, 8173, 8174, 8175, 8176, 8178, 8180, 8181, 8183, 8187, 8188, 8197, 8198, 8199, 8202, 8204, 8205, 8208, 8211, 8215, 8216, 8220, 8225, 8227, 8231, 8232, 8233, 8238, 8239, 8246, 8247, 8250, 8252, 8255, 8258, 8259, 8262, 8263, 8267, 8269, 8270, 8273, 8281, 8283, 8284, 8286, 8290, 8297, 8298, 8303, 8305, 8306, 8311, 8312, 8314, 8319, 8320, 8321, 8322, 8323, 8324, 8328, 8329, 8330, 8333, 8335, 8339, 8341, 8342, 8343, 8347, 8358, 8360, 8368, 8369, 8371, 8372, 8373, 8374, 8375, 8376, 8377, 8378, 8379, 8380, 8382, 8386, 8390, 8396, 8397, 8398, 8399, 8400, 8401, 8408, 8411, 8413, 8414, 8416, 8421, 8422, 8427, 8429, 8434, 8445, 8448, 8453, 8455, 8457, 8459, 8463, 8466, 8468, 8469, 8471, 8477, 8482, 8483, 8488, 8489, 8495, 8497, 8498, 8499, 8501, 8502, 8504, 8508, 8510, 8516, 8517, 8520, 8525, 8528, 8530, 8539, 8541, 8542, 8552, 8555, 8559, 8564, 8566, 8567, 8569, 8574, 8575, 8578, 8580, 8582, 8583, 8586, 8592, 8593, 8595, 8598, 8599, 8600, 8601, 8603, 8604, 8607, 8611, 8616, 8617, 8620, 8621, 8634, 8636, 8638, 8640, 8641, 8653, 8654, 8655, 8656, 8658, 8663, 8666, 8667, 8668, 8669, 8671, 8672, 8673, 8677, 8678, 8680, 8685, 8687, 8690, 8692, 8693, 8694, 8695, 8697, 8698, 8699, 8700, 8702, 8703, 8707, 8710, 8711, 8713, 8715, 8716, 8720, 8721, 8722, 8725, 8731, 8732, 8736, 8737, 8742, 8743, 8744, 8747, 8750, 8751, 8756, 8757, 8758, 8762, 8770, 8782, 8784, 8785, 8786, 8789, 8793, 8795, 8800, 8801, 8803, 8804, 8806, 8810, 8811, 8813, 8817, 8821, 8823, 8824, 8827, 8828, 8830, 8833, 8839, 8841, 8842, 8848, 8850, 8856, 8857, 8862, 8864, 8865, 8868, 8869, 8875, 8877, 8881, 8884, 8885, 8886, 8887, 8891, 8897, 8900, 8903, 8904, 8905, 8906, 8908, 8910, 8911, 8912, 8913, 8916, 8917, 8921, 8922, 8929, 8931, 8934, 8935, 8936, 8940, 8941, 8942, 8945, 8946, 8947, 8951, 8954, 8956, 8960, 8962, 8963, 8965, 8966, 8968, 8975, 8977, 8978, 8979, 8980, 8989, 8990, 8997, 8998, 9000, 9004, 9006, 9007, 9009, 9014, 9018, 9022, 9028, 9029, 9030, 9031, 9033, 9045, 9046, 9048, 9049, 9050, 9051, 9052, 9053, 9054, 9055, 9056, 9057, 9060, 9063, 9064, 9066, 9067, 9068, 9069, 9071, 9075, 9076, 9077, 9079, 9080, 9084, 9086, 9088, 9092, 9093, 9095, 9096, 9100, 9103, 9105, 9108, 9112, 9116, 9118, 9120, 9123, 9124, 9125, 9126, 9127, 9129, 9131, 9134, 9138, 9139, 9141, 9142, 9143, 9144, 9146, 9147, 9148, 9149, 9152, 9156, 9157, 9159, 9162, 9163, 9167, 9169, 9175, 9178, 9179, 9182, 9184, 9188, 9189, 9190, 9193, 9194, 9196, 9197, 9199, 9201, 9202, 9204, 9205, 9206, 9207, 9210, 9214, 9217, 9221, 9222, 9228, 9229, 9231, 9235, 9239, 9240, 9241, 9245, 9248, 9251, 9253, 9257, 9258, 9259, 9262, 9265, 9268, 9269, 9270, 9272, 9275, 9278, 9279, 9282, 9284, 9287, 9288, 9291, 9296, 9301, 9302, 9303, 9304, 9305, 9306, 9307, 9309, 9313, 9315, 9317, 9320, 9322, 9323, 9324, 9325, 9326, 9330, 9332, 9333, 9334, 9335, 9337, 9338, 9340, 9342, 9344, 9345, 9347, 9348, 9349, 9352, 9353, 9355, 9362, 9366, 9367, 9369, 9371, 9376, 9379, 9380, 9381, 9382, 9385, 9386, 9388, 9389, 9390, 9395, 9397, 9400, 9402, 9404, 9405, 9407, 9414, 9416, 9421, 9424, 9425, 9428, 9430, 9432, 9433, 9434, 9436, 9437, 9442, 9444, 9447, 9449, 9451, 9452, 9453, 9454, 9455, 9460, 9461, 9463, 9464, 9465, 9466, 9467, 9468, 9471, 9473, 9476, 9478, 9479, 9480, 9488, 9491, 9494, 9500, 9501, 9505, 9506, 9508, 9516, 9517, 9519, 9520, 9521, 9522, 9524, 9531, 9534, 9536, 9537, 9541, 9544, 9545, 9547, 9549, 9552, 9554, 9556, 9557, 9558, 9561, 9562, 9563, 9566, 9567, 9569, 9570, 9571, 9574, 9575, 9579, 9581, 9582, 9587, 9589, 9591, 9593, 9595, 9596, 9597, 9599, 9600, 9602, 9605, 9606, 9608, 9611, 9612, 9614, 9616, 9617, 9619, 9620, 9621, 9624, 9630, 9633, 9641, 9642, 9645, 9649, 9651, 9652, 9657, 9658, 9659, 9663, 9665, 9666, 9669, 9672, 9674, 9678, 9679, 9683, 9684, 9686, 9687, 9689, 9690, 9691, 9692, 9694, 9698, 9699, 9701, 9702, 9704, 9706, 9707, 9710, 9715, 9722, 9728, 9732, 9735, 9736, 9739, 9740, 9741, 9744, 9745, 9746, 9747, 9748, 9749, 9752, 9753, 9756, 9758, 9760, 9762, 9764, 9765, 9767, 9768, 9773, 9775, 9776, 9777, 9778, 9779, 9781, 9783, 9786, 9789, 9792, 9794, 9798, 9799, 9802, 9805, 9807, 9808, 9809, 9814, 9815, 9817, 9822, 9824, 9827, 9832, 9837, 9839, 9842, 9843, 9845, 9847, 9848, 9849, 9856, 9858, 9859, 9861, 9863, 9864, 9865, 9866, 9869, 9870, 9871, 9874, 9875, 9876, 9878, 9880, 9881, 9883, 9886, 9887, 9890, 9893, 9899, 9900, 9908, 9909, 9911, 9912, 9913, 9914, 9915, 9919, 9921, 9924, 9925, 9926, 9930, 9932, 9937, 9938, 9941, 9945, 9947, 9948, 9949, 9950, 9951, 9955, 9958, 9962, 9963, 9964, 9965, 9966, 9969, 9973, 9974, 9975, 9983, 9984, 9986, 9988, 9992, 9994, 9995, 10000, 10004, 10005, 10006, 10007, 10009, 10011, 10012, 10014, 10015, 10016, 10017, 10018, 10020, 10025, 10026, 10027, 10028, 10029, 10041, 10042, 10045, 10046, 10047, 10048, 10050, 10052, 10054, 10059, 10060, 10061, 10062, 10063, 10065, 10068, 10069, 10070, 10071, 10073, 10074, 10079, 10080, 10082, 10083, 10084, 10085, 10087, 10089, 10090, 10091, 10092, 10094, 10095, 10097, 10099, 10100, 10102, 10104, 10105, 10106, 10110, 10111, 10113, 10115, 10118, 10120, 10126, 10131, 10134, 10135, 10136, 10137, 10141, 10142, 10147, 10149, 10150, 10151, 10152, 10156, 10161, 10162, 10163, 10166, 10168, 10172, 10174, 10175, 10176, 10180, 10184, 10186, 10187, 10189, 10192, 10196, 10198, 10199, 10204, 10208, 10211, 10212, 10214, 10215, 10219, 10220, 10221, 10225, 10226, 10227, 10228, 10229, 10230, 10231, 10233, 10234, 10236, 10237, 10239, 10244, 10245, 10247, 10249, 10250, 10253, 10254, 10261, 10265, 10266, 10267, 10268, 10270, 10271, 10279, 10281, 10282, 10284, 10286, 10287, 10288, 10291, 10293, 10297, 10300, 10301, 10302, 10304, 10306, 10308, 10310, 10312, 10313, 10314, 10315, 10317, 10323, 10326, 10327, 10328, 10331, 10332, 10335, 10336, 10337, 10338, 10342, 10344, 10345, 10346, 10348, 10350, 10352, 10354, 10357, 10360, 10365, 10366, 10368, 10370, 10373, 10380, 10382, 10383, 10384, 10385, 10387, 10388, 10393, 10394, 10396, 10397, 10399, 10402, 10406, 10407, 10409, 10411, 10412, 10414, 10416, 10417, 10418, 10419, 10420, 10422, 10426, 10428, 10433, 10438, 10439, 10440, 10443, 10444, 10448, 10449, 10451, 10452, 10455, 10456, 10457, 10459, 10460, 10461, 10463, 10464, 10465, 10466, 10468, 10469, 10470, 10471, 10472, 10473, 10474, 10478, 10479, 10480, 10483, 10484, 10492, 10493, 10494, 10496, 10497, 10499, 10502, 10503, 10504, 10506, 10512, 10514, 10516, 10519, 10523, 10525, 10529, 10531, 10532, 10533, 10537, 10538, 10539, 10544, 10546, 10547, 10560, 10562, 10563, 10566, 10570, 10571, 10572, 10573, 10574, 10575, 10577, 10578, 10580, 10581, 10583, 10585, 10586, 10587, 10588, 10590, 10591, 10593, 10594, 10595, 10596, 10597, 10600, 10602, 10603, 10605, 10606, 10608, 10609, 10612, 10615, 10618, 10622, 10625, 10626, 10627, 10628, 10630, 10631, 10634, 10635, 10636, 10637, 10638, 10639, 10641, 10642, 10648, 10649, 10650], "Game Republic, JapanStudio": [4079], "SNK Playmore": [3954, 3981, 4215, 4647, 5443, 5502, 6018, 6180, 6220, 6956, 7017, 7027, 7755, 8080, 8158, 8185, 8464, 8888, 9186, 9929, 10540], "NetherRealm Studios": [376, 581, 1026, 1252, 5532], "Aki Corp.": [639, 732, 2731, 4748, 5077], "Brash Entertainment": [3855, 8890], "Big Huge Games": [1760, 1800, 4205, 8229, 9059, 9311], "Io Interactive, Nixxes Software": [4809], "Activision": [778, 1637, 2586, 2600, 2969, 3080, 3492, 3713, 3780, 3786, 3974, 4091, 4417, 4458, 4554, 4942, 5002, 5040, 5163, 5394, 5430, 5568, 5578, 5582, 5616, 5620, 5729, 5807, 5975, 6148, 6151, 6261, 6295, 6507, 6561, 6577, 6601, 6664, 6676, 6736, 6739, 6823, 6891, 7095, 7224, 7240, 7533, 7808, 7954, 8325, 8748, 9417, 9784, 9816, 10425], "Twisted Pixel Games": [3518], "High Moon Studios, Mercenary Technologies": [10584], "Idea Factory, Compile Heart": [3292, 6009, 6290], "TimeGate Studios": [4570, 9274, 10450], "Presto Studios": [4454, 8436], "The Fun Pimps Entertainment LLC": [6416, 8531], "Digital Anvil": [1840, 8769], "Arcade Moon": [3708, 3779, 4483], "SCE Studio Cambridge": [4213, 4797, 7502], "Gaijin Entertainment": [2187, 2868, 4926, 5390, 5981, 6134, 6404, 6532, 7186, 7334, 9336], "Neversoft Entertainment": [141, 159, 169, 178, 226, 246, 318, 419, 498, 532, 658, 1148, 1201, 1257, 1324, 1367, 1528, 1626, 1631, 1789, 1856, 1886, 1902, 1928, 2017, 2026, 2139, 2377, 2381, 2395, 2565, 2654, 2688, 2841, 2935, 2954, 3222, 3334, 3848, 4049, 4404, 4462, 4523, 5706, 7234, 9401], "Edmund McMillen, Florian Himsl": [9364], "Team Ninja": [726, 1070, 1193, 1303, 1805, 2335, 2511, 2924, 3084, 3273, 4041, 4405, 4711, 4799, 7449, 8591], "Activision Value": [4689, 8302, 10495], "Zener Works": [3767], "Micro Cabin": [7015, 8562, 9583], "High Voltage Software, Backbone Entertainment": [3871, 5739, 7060], "AWE Games": [2906, 4453, 7722, 7951], "Vingt-et-un Systems": [1299, 1384, 9114], "Capcom Vancouver": [871, 4036, 4482, 8365], "Kheops Studio": [7764], "Natsume": [2059, 4962, 9290, 9497], "Climax Group": [1233, 1453, 2489, 2513, 3181, 3345, 3731, 3931, 4374, 4998, 5161, 5510, 5974, 6586, 7206, 7362, 7396, 7403, 7420, 7762, 8017, 8059, 8418, 8534, 8632, 9299, 9857, 10033], "Kamui": [3294], "Ironclad Games": [9230, 9493], "Big Sky Software": [1383, 5406, 7603], "NEC Interchannel": [9486], "Swingin' Ape": [5803, 7171], "Warner Bros. Interactive Entertainment, NetherRealm Studios": [397, 1032], "Void Productions": [6987], "Career Soft": [5127, 6941], "2XL Games": [5244, 5418], "Blue Omega": [7554, 8074], "Evolution Studios": [230, 598, 1058, 3002, 7528], "Griffin International": [5029, 7503], "Spark Unlimited, comcept": [7500, 8846], "Ready at Dawn, SCE Santa Monica": [755, 1854], "Banpresto": [4267], "Loose Cannon Studios": [7353, 7534, 7745], "Rockstar London": [2651], "Spark Unlimited": [367, 1218, 4322, 4664, 4835, 5294, 6571, 6861, 9150, 10093], "Ambrella": [3663], "Pseudo Interactive": [5147, 5754, 6766, 8261], "ProSoft": [7474], "KING Art": [7152, 8142, 10404, 10446], "Kouyousha": [2015, 3316], "Argonaut Games": [239, 629, 3283, 3537, 4015, 5239, 5821, 5878, 5955, 7385, 7457, 7982, 8097, 8235, 8556, 8619, 9999, 10400, 10510], "Takara Tomy": [7545, 7841], "Clap Hanz": [365, 1310, 1700, 4362], "I-Imagine": [6753], "Dearsoft": [2077], "Hothouse Creations": [2708, 8763], "Junction Point": [341, 4990], "Global Star Software": [10610], "Tantalus Interactive": [5249, 5414, 7818], "Square Enix": [103, 120, 185, 424, 561, 595, 939, 948, 1411, 1565, 1888, 2064, 2193, 2530, 2725, 3308, 3469, 3580, 3939, 4043, 4224, 4511, 4540, 4702, 4791, 5006, 5484, 6178, 6181, 6600, 7837, 9713, 9717, 10349], "Curly Monsters": [6685], "Eighting": [2767, 3628, 4557, 5977, 7455, 8245], "Zeroscale": [6841], "S-Neo": [7602, 8057], "Volition Inc., CD Projekt Red Studio, CD Projekt, CD Projekt Localisation Centre": [9198], "Frogwares": [4903, 6094, 8124, 10056, 10410, 10534], "Digital Embryo": [7521], "Blue Shift": [4594, 4755, 6166, 8571, 9795], "Atlus Co.": [1867, 2365, 3168, 3618, 3827, 6525, 6619, 7714], "Beyond Reality": [5108, 8930], "1C, Various, 1C Company": [10381], "BudCat": [713, 1335, 1908, 3445, 7374, 7425, 7431], "Metro": [4619, 6738], "Rockstar Vienna": [1081], "AI": [4004], "Shift": [7098, 8538], "Other Ocean Interactive": [7322, 9135, 9472, 10010], "Studio Liverpool": [4674, 4721, 8206], "Papyrus": [10561], "Krome Studios, Screenlife Games": [2286], "Iridon Interactive AB": [9081], "Ubisoft Paris, Ubisoft Montpellier": [182, 618], "Examu": [5431, 6083, 7134, 8682], "Coyote Developments": [5662, 7122, 7920], "Nvizzio Creations": [9976], "Cyanide": [5945, 8714, 9010, 9242, 9249, 9255, 10121, 10611], "SystemSoft": [8933], "Yuke's": [437, 503, 599, 987, 1004, 1091, 1093, 1153, 1186, 1220, 1261, 1268, 1296, 1304, 1350, 1378, 1401, 1450, 1466, 1523, 1538, 1613, 1657, 1751, 1842, 1934, 2062, 2314, 2479, 2507, 2601, 2720, 2888, 2901, 2958, 3118, 3179, 3296, 3545, 3557, 3667, 3676, 3885, 3903, 3947, 4563, 4615, 6371, 7125, 7219, 9565], "Splash Damage": [1464, 2067, 5719, 10272], "Gulti": [7665], "Toys for Bob": [395, 452, 1106, 1115, 1427, 1557, 1597, 1610, 1708, 2142, 2240, 2255, 2396, 3214, 3669, 4075, 4438, 4745, 4965, 4978, 5680, 6347, 6831, 7009, 7140, 7359, 7378, 7531], "JoWooD Entertainment AG": [9927], "Game Republic": [2003, 4163, 4356, 4996, 5511, 5964, 7733, 7813], "Fatshark AB": [7966, 8047], "2K Sports": [2436, 3328, 4614, 4703, 5168, 5190, 5742, 5787, 5860, 6078, 6231, 6800, 7299, 7303, 7306, 8228], "Spike": [815, 1890, 1907, 1970, 2330, 2437, 2748, 2884, 4368, 4617, 8249, 9286, 10598], "Digital Mayhem": [7226, 8310, 9212], "The Odd Gentlemen": [10305], "Pyramid": [2174, 4464], "PLAYGROUND, Playground Games": [633], "Vir2L Studios": [3819], "Bungie Software": [46, 88, 2168], "Battlefront.com, 1C, 1C Company": [10395], "Funbox Media": [10169], "Mahou": [4220], "PlatinumGames": [1001, 1632, 1956, 1981, 2427, 3017, 3385, 3501, 3755, 5014, 5299, 5886, 6424, 7443, 7716, 7743, 8633, 8915, 8948, 9409], "Ronin Entertainment": [4191], "Double Fine Productions": [1549, 1615, 2825, 6835], "Infinite Machine": [7470], "Media Vision": [4407, 5358, 6299, 6993, 7298, 7466, 9360], "TOYBOX": [8486], "Tranji": [10098], "Tomy Corporation": [2197, 6165], "Marvelous Inc.": [5731, 7142, 10462], "UGA": [7775, 8570], "Attractive Games": [8120]}, "name": "Developer"}